Workbook

Sheet Fake Live Dashboard
A1: IT Simplification — FY27 Cost-out Dashboard
A2: Actual savings achieved, remaining opportunity and timing by quarter
A4: V1 BUDGET | D4: ENTERED RENEWAL PRICE | G4: NET IDENTIFIED COSTOUT | I4: FINALISED POSITIVE COSTOUT
A5: =B24 -> 23692506 | D5: =C24 -> 22962976 | G5: =D24 -> 728974.63 | I5: =E24 -> 320983.41
A7: ="The tracked V1 budget is "&TEXT(A5,"$#,##0")&" and entered renewal prices total "&TEXT(D5,"$#,##0")&". The signed net identified costout in Column J is "&TEXT(G5,"$#,##0")&". Of the "&TEXT(E24+F24,"$#,##0")&" gross positive costout identified, "&TEXT(I5,"$#,##0")&" is finalised ("&TEXT(IFERROR(E24/(E24+F24),0),"0.0%")&"); "&TEXT(G24,"$#,##0")&" is separately classified as budget variance / reclassification." -> The tracked V1 budget is $23,692,506 and entered renewal prices total $22,962,976. The signed net identified costout in Column J is $728,975. Of the $1,009,252 gross positive costout identified, $320,983 is finalised (31.8%); $280,277 is separately classified as budget variance / reclassification.
A10: QUARTERLY BUDGET, RENEWAL AND COSTOUT OUTLOOK
A11: Metric | B11: Q1 FY27 | C11: Q2 FY27 | D11: Q3 FY27 | E11: Q4 FY27 | F11: Unscheduled | G11: FY27 Total
A12: V1 budget | B12: {=SUM(SUMIFS('Fake Simplified View'!$F$2:$F$143,'Fake Simplified View'!$D$2:$D$143,{"Licensing","Consumption","New spend","Microsoft"},'Fake Simplified View'!$E$2:$E$143,">="&DATE(2026,7,1),'Fake Simplified View'!$E$2:$E$143,"<"&DATE(2026,10,1)))} -> 844008.17 | C12: {=SUM(SUMIFS('Fake Simplified View'!$F$2:$F$143,'Fake Simplified View'!$D$2:$D$143,{"Licensing","Consumption","New spend","Microsoft"},'Fake Simplified View'!$E$2:$E$143,">="&DATE(2026,10,1),'Fake Simplified View'!$E$2:$E$143,"<"&DATE(2027,1,1)))} -> 3477136.3 | D12: {=SUM(SUMIFS('Fake Simplified View'!$F$2:$F$143,'Fake Simplified View'!$D$2:$D$143,{"Licensing","Consumption","New spend","Microsoft"},'Fake Simplified View'!$E$2:$E$143,">="&DATE(2027,1,1),'Fake Simplified View'!$E$2:$E$143,"<"&DATE(2027,4,1)))} -> 1175842.5 | E12: {=SUM(SUMIFS('Fake Simplified View'!$F$2:$F$143,'Fake Simplified View'!$D$2:$D$143,{"Licensing","Consumption","New spend","Microsoft"},'Fake Simplified View'!$E$2:$E$143,">="&DATE(2027,4,1),'Fake Simplified View'!$E$2:$E$143,"<"&DATE(2027,7,1)))} -> 1272025.9 | F12: {=SUMPRODUCT(--ISNUMBER(MATCH('Fake Simplified View'!$D$2:$D$143,{"Licensing","Consumption","New spend","Microsoft"},0)),--IF(ISNUMBER('Fake Simplified View'!$E$2:$E$143),(('Fake Simplified View'!$E$2:$E$143<DATE(2026,7,1))+('Fake Simplified View'!$E$2:$E$143>=DATE(2027,7,1))>0),TRUE),'Fake Simplified View'!$F$2:$F$143)} -> 16923494 | G12: =B24 -> 23692506
A13: Entered renewal price | B13: {=SUM(SUMIFS('Fake Simplified View'!$G$2:$G$143,'Fake Simplified View'!$D$2:$D$143,{"Licensing","Consumption","New spend","Microsoft"},'Fake Simplified View'!$E$2:$E$143,">="&DATE(2026,7,1),'Fake Simplified View'!$E$2:$E$143,"<"&DATE(2026,10,1)))} -> 588167.13 | C13: {=SUM(SUMIFS('Fake Simplified View'!$G$2:$G$143,'Fake Simplified View'!$D$2:$D$143,{"Licensing","Consumption","New spend","Microsoft"},'Fake Simplified View'!$E$2:$E$143,">="&DATE(2026,10,1),'Fake Simplified View'!$E$2:$E$143,"<"&DATE(2027,1,1)))} -> 3379516.7 | D13: {=SUM(SUMIFS('Fake Simplified View'!$G$2:$G$143,'Fake Simplified View'!$D$2:$D$143,{"Licensing","Consumption","New spend","Microsoft"},'Fake Simplified View'!$E$2:$E$143,">="&DATE(2027,1,1),'Fake Simplified View'!$E$2:$E$143,"<"&DATE(2027,4,1)))} -> 1172578.4 | E13: {=SUM(SUMIFS('Fake Simplified View'!$G$2:$G$143,'Fake Simplified View'!$D$2:$D$143,{"Licensing","Consumption","New spend","Microsoft"},'Fake Simplified View'!$E$2:$E$143,">="&DATE(2027,4,1),'Fake Simplified View'!$E$2:$E$143,"<"&DATE(2027,7,1)))} -> 1264749.7 | F13: {=SUMPRODUCT(--ISNUMBER(MATCH('Fake Simplified View'!$D$2:$D$143,{"Licensing","Consumption","New spend","Microsoft"},0)),--IF(ISNUMBER('Fake Simplified View'!$E$2:$E$143),(('Fake Simplified View'!$E$2:$E$143<DATE(2026,7,1))+('Fake Simplified View'!$E$2:$E$143>=DATE(2027,7,1))>0),TRUE),'Fake Simplified View'!$G$2:$G$143)} -> 16557964 | G13: =C24 -> 22962976
A14: Net identified costout | B14: {=SUM(SUMIFS('Fake Simplified View'!$H$2:$H$143,'Fake Simplified View'!$D$2:$D$143,{"Licensing","Consumption","New spend","Microsoft"},'Fake Simplified View'!$E$2:$E$143,">="&DATE(2026,7,1),'Fake Simplified View'!$E$2:$E$143,"<"&DATE(2026,10,1)))} -> 255841.04 | C14: {=SUM(SUMIFS('Fake Simplified View'!$H$2:$H$143,'Fake Simplified View'!$D$2:$D$143,{"Licensing","Consumption","New spend","Microsoft"},'Fake Simplified View'!$E$2:$E$143,">="&DATE(2026,10,1),'Fake Simplified View'!$E$2:$E$143,"<"&DATE(2027,1,1)))} -> 97619.637 | D14: {=SUM(SUMIFS('Fake Simplified View'!$H$2:$H$143,'Fake Simplified View'!$D$2:$D$143,{"Licensing","Consumption","New spend","Microsoft"},'Fake Simplified View'!$E$2:$E$143,">="&DATE(2027,1,1),'Fake Simplified View'!$E$2:$E$143,"<"&DATE(2027,4,1)))} -> 2708.36 | E14: {=SUM(SUMIFS('Fake Simplified View'!$H$2:$H$143,'Fake Simplified View'!$D$2:$D$143,{"Licensing","Consumption","New spend","Microsoft"},'Fake Simplified View'!$E$2:$E$143,">="&DATE(2027,4,1),'Fake Simplified View'!$E$2:$E$143,"<"&DATE(2027,7,1)))} -> 7276.18 | F14: {=SUMPRODUCT(--ISNUMBER(MATCH('Fake Simplified View'!$D$2:$D$143,{"Licensing","Consumption","New spend","Microsoft"},0)),--IF(ISNUMBER('Fake Simplified View'!$E$2:$E$143),(('Fake Simplified View'!$E$2:$E$143<DATE(2026,7,1))+('Fake Simplified View'!$E$2:$E$143>=DATE(2027,7,1))>0),TRUE),'Fake Simplified View'!$H$2:$H$143)} -> 365529.41 | G14: =D24 -> 728974.63
A15: Finalised positive costout | B15: {=SUM(SUMIFS('Fake Simplified View'!$H$2:$H$143,'Fake Simplified View'!$D$2:$D$143,{"Licensing","Consumption","New spend","Microsoft"},'Fake Simplified View'!$C$2:$C$143,"Y",'Fake Simplified View'!$H$2:$H$143,">0",'Fake Simplified View'!$E$2:$E$143,">="&DATE(2026,7,1),'Fake Simplified View'!$E$2:$E$143,"<"&DATE(2026,10,1)))} -> 27820.323 | C15: {=SUM(SUMIFS('Fake Simplified View'!$H$2:$H$143,'Fake Simplified View'!$D$2:$D$143,{"Licensing","Consumption","New spend","Microsoft"},'Fake Simplified View'!$C$2:$C$143,"Y",'Fake Simplified View'!$H$2:$H$143,">0",'Fake Simplified View'!$E$2:$E$143,">="&DATE(2026,10,1),'Fake Simplified View'!$E$2:$E$143,"<"&DATE(2027,1,1)))} -> 22095.13 | D15: {=SUM(SUMIFS('Fake Simplified View'!$H$2:$H$143,'Fake Simplified View'!$D$2:$D$143,{"Licensing","Consumption","New spend","Microsoft"},'Fake Simplified View'!$C$2:$C$143,"Y",'Fake Simplified View'!$H$2:$H$143,">0",'Fake Simplified View'!$E$2:$E$143,">="&DATE(2027,1,1),'Fake Simplified View'!$E$2:$E$143,"<"&DATE(2027,4,1)))} -> 0 | E15: {=SUM(SUMIFS('Fake Simplified View'!$H$2:$H$143,'Fake Simplified View'!$D$2:$D$143,{"Licensing","Consumption","New spend","Microsoft"},'Fake Simplified View'!$C$2:$C$143,"Y",'Fake Simplified View'!$H$2:$H$143,">0",'Fake Simplified View'!$E$2:$E$143,">="&DATE(2027,4,1),'Fake Simplified View'!$E$2:$E$143,"<"&DATE(2027,7,1)))} -> 0 | F15: {=SUMPRODUCT(--ISNUMBER(MATCH('Fake Simplified View'!$D$2:$D$143,{"Licensing","Consumption","New spend","Microsoft"},0)),--IF(ISNUMBER('Fake Simplified View'!$E$2:$E$143),(('Fake Simplified View'!$E$2:$E$143<DATE(2026,7,1))+('Fake Simplified View'!$E$2:$E$143>=DATE(2027,7,1))>0),TRUE),--(UPPER(TRIM('Fake Simplified View'!$C$2:$C$143))="Y"),--('Fake Simplified View'!$H$2:$H$143>0),'Fake Simplified View'!$H$2:$H$143)} -> 271067.96 | G15: =E24 -> 320983.41
A16: Unfinalised positive costout | B16: {=SUM(SUMIFS('Fake Simplified View'!$H$2:$H$143,'Fake Simplified View'!$D$2:$D$143,{"Licensing","Consumption","New spend","Microsoft"},'Fake Simplified View'!$C$2:$C$143,"<>Y",'Fake Simplified View'!$H$2:$H$143,">0",'Fake Simplified View'!$E$2:$E$143,">="&DATE(2026,7,1),'Fake Simplified View'!$E$2:$E$143,"<"&DATE(2026,10,1)))} -> 230609.96 | C16: {=SUM(SUMIFS('Fake Simplified View'!$H$2:$H$143,'Fake Simplified View'!$D$2:$D$143,{"Licensing","Consumption","New spend","Microsoft"},'Fake Simplified View'!$C$2:$C$143,"<>Y",'Fake Simplified View'!$H$2:$H$143,">0",'Fake Simplified View'!$E$2:$E$143,">="&DATE(2026,10,1),'Fake Simplified View'!$E$2:$E$143,"<"&DATE(2027,1,1)))} -> 111226.91 | D16: {=SUM(SUMIFS('Fake Simplified View'!$H$2:$H$143,'Fake Simplified View'!$D$2:$D$143,{"Licensing","Consumption","New spend","Microsoft"},'Fake Simplified View'!$C$2:$C$143,"<>Y",'Fake Simplified View'!$H$2:$H$143,">0",'Fake Simplified View'!$E$2:$E$143,">="&DATE(2027,1,1),'Fake Simplified View'!$E$2:$E$143,"<"&DATE(2027,4,1)))} -> 3088.36 | E16: {=SUM(SUMIFS('Fake Simplified View'!$H$2:$H$143,'Fake Simplified View'!$D$2:$D$143,{"Licensing","Consumption","New spend","Microsoft"},'Fake Simplified View'!$C$2:$C$143,"<>Y",'Fake Simplified View'!$H$2:$H$143,">0",'Fake Simplified View'!$E$2:$E$143,">="&DATE(2027,4,1),'Fake Simplified View'!$E$2:$E$143,"<"&DATE(2027,7,1)))} -> 48881.52 | F16: {=SUMPRODUCT(--ISNUMBER(MATCH('Fake Simplified View'!$D$2:$D$143,{"Licensing","Consumption","New spend","Microsoft"},0)),--IF(ISNUMBER('Fake Simplified View'!$E$2:$E$143),(('Fake Simplified View'!$E$2:$E$143<DATE(2026,7,1))+('Fake Simplified View'!$E$2:$E$143>=DATE(2027,7,1))>0),TRUE),--(UPPER(TRIM('Fake Simplified View'!$C$2:$C$143))<>"Y"),--('Fake Simplified View'!$H$2:$H$143>0),'Fake Simplified View'!$H$2:$H$143)} -> 294461.45 | G16: =F24 -> 688268.2
A17: Budget variance / reclassification | B17: {=-SUM(SUMIFS('Fake Simplified View'!$H$2:$H$143,'Fake Simplified View'!$D$2:$D$143,{"Licensing","Consumption","New spend","Microsoft"},'Fake Simplified View'!$H$2:$H$143,"<0",'Fake Simplified View'!$E$2:$E$143,">="&DATE(2026,7,1),'Fake Simplified View'!$E$2:$E$143,"<"&DATE(2026,10,1)))} -> 2589.24 | C17: {=-SUM(SUMIFS('Fake Simplified View'!$H$2:$H$143,'Fake Simplified View'!$D$2:$D$143,{"Licensing","Consumption","New spend","Microsoft"},'Fake Simplified View'!$H$2:$H$143,"<0",'Fake Simplified View'!$E$2:$E$143,">="&DATE(2026,10,1),'Fake Simplified View'!$E$2:$E$143,"<"&DATE(2027,1,1)))} -> 35702.4 | D17: {=-SUM(SUMIFS('Fake Simplified View'!$H$2:$H$143,'Fake Simplified View'!$D$2:$D$143,{"Licensing","Consumption","New spend","Microsoft"},'Fake Simplified View'!$H$2:$H$143,"<0",'Fake Simplified View'!$E$2:$E$143,">="&DATE(2027,1,1),'Fake Simplified View'!$E$2:$E$143,"<"&DATE(2027,4,1)))} -> 380 | E17: {=-SUM(SUMIFS('Fake Simplified View'!$H$2:$H$143,'Fake Simplified View'!$D$2:$D$143,{"Licensing","Consumption","New spend","Microsoft"},'Fake Simplified View'!$H$2:$H$143,"<0",'Fake Simplified View'!$E$2:$E$143,">="&DATE(2027,4,1),'Fake Simplified View'!$E$2:$E$143,"<"&DATE(2027,7,1)))} -> 41605.34 | F17: {=-SUMPRODUCT(--ISNUMBER(MATCH('Fake Simplified View'!$D$2:$D$143,{"Licensing","Consumption","New spend","Microsoft"},0)),--IF(ISNUMBER('Fake Simplified View'!$E$2:$E$143),(('Fake Simplified View'!$E$2:$E$143<DATE(2026,7,1))+('Fake Simplified View'!$E$2:$E$143>=DATE(2027,7,1))>0),TRUE),--('Fake Simplified View'!$H$2:$H$143<0),'Fake Simplified View'!$H$2:$H$143)} -> 200000.01 | G17: =G24 -> 280276.99
A19: CATEGORY BUDGET, RENEWAL AND COSTOUT OUTLOOK
A20: Category | B20: V1 budget | C20: Entered renewal price | D20: Net identified costout | E20: Finalised positive costout | F20: Unfinalised positive costout | G20: Budget variance / reclassification
A21: Licensing | B21: =SUMIFS('Fake Simplified View'!$F$2:$F$143,'Fake Simplified View'!$D$2:$D$143,$A21) -> 15574045 | C21: =SUMIFS('Fake Simplified View'!$G$2:$G$143,'Fake Simplified View'!$D$2:$D$143,$A21) -> 14844915 | D21: =SUMIFS('Fake Simplified View'!$H$2:$H$143,'Fake Simplified View'!$D$2:$D$143,$A21) -> 728574.63 | E21: =SUMIFS('Fake Simplified View'!$H$2:$H$143,'Fake Simplified View'!$D$2:$D$143,$A21,'Fake Simplified View'!$C$2:$C$143,"Y",'Fake Simplified View'!$H$2:$H$143,">0") -> 320983.41 | F21: =SUMIFS('Fake Simplified View'!$H$2:$H$143,'Fake Simplified View'!$D$2:$D$143,$A21,'Fake Simplified View'!$C$2:$C$143,"<>Y",'Fake Simplified View'!$H$2:$H$143,">0") -> 687868.2 | G21: =-SUMIFS('Fake Simplified View'!$H$2:$H$143,'Fake Simplified View'!$D$2:$D$143,$A21,'Fake Simplified View'!$H$2:$H$143,"<0") -> 280276.99 | I21: Net identified costout: Overall expected reduction based on all values currently entered
A22: Consumption | B22: =SUMIFS('Fake Simplified View'!$F$2:$F$143,'Fake Simplified View'!$D$2:$D$143,$A22) -> 7659712.8 | C22: =SUMIFS('Fake Simplified View'!$G$2:$G$143,'Fake Simplified View'!$D$2:$D$143,$A22) -> 7659312.8 | D22: =SUMIFS('Fake Simplified View'!$H$2:$H$143,'Fake Simplified View'!$D$2:$D$143,$A22) -> 400.00259 | E22: =SUMIFS('Fake Simplified View'!$H$2:$H$143,'Fake Simplified View'!$D$2:$D$143,$A22,'Fake Simplified View'!$C$2:$C$143,"Y",'Fake Simplified View'!$H$2:$H$143,">0") -> 0 | F22: =SUMIFS('Fake Simplified View'!$H$2:$H$143,'Fake Simplified View'!$D$2:$D$143,$A22,'Fake Simplified View'!$C$2:$C$143,"<>Y",'Fake Simplified View'!$H$2:$H$143,">0") -> 400.00259 | G22: =-SUMIFS('Fake Simplified View'!$H$2:$H$143,'Fake Simplified View'!$D$2:$D$143,$A22,'Fake Simplified View'!$H$2:$H$143,"<0") -> 0 | I22: Finalised positive costout: Savings confirmed/completed
A23: New Spend | B23: =SUMIFS('Fake Simplified View'!$F$2:$F$143,'Fake Simplified View'!$D$2:$D$143,$A23) -> 458748.67 | C23: =SUMIFS('Fake Simplified View'!$G$2:$G$143,'Fake Simplified View'!$D$2:$D$143,$A23) -> 458748.67 | D23: =SUMIFS('Fake Simplified View'!$H$2:$H$143,'Fake Simplified View'!$D$2:$D$143,$A23) -> 0 | E23: =SUMIFS('Fake Simplified View'!$H$2:$H$143,'Fake Simplified View'!$D$2:$D$143,$A23,'Fake Simplified View'!$C$2:$C$143,"Y",'Fake Simplified View'!$H$2:$H$143,">0") -> 0 | F23: =SUMIFS('Fake Simplified View'!$H$2:$H$143,'Fake Simplified View'!$D$2:$D$143,$A23,'Fake Simplified View'!$C$2:$C$143,"<>Y",'Fake Simplified View'!$H$2:$H$143,">0") -> 0 | G23: =-SUMIFS('Fake Simplified View'!$H$2:$H$143,'Fake Simplified View'!$D$2:$D$143,$A23,'Fake Simplified View'!$H$2:$H$143,"<0") -> 0 | I23: Unfinalised positive costout: Savings pipeline - not guaranteed savings
A24: Total | B24: =SUM(B21:B23) -> 23692506 | C24: =SUM(C21:C23) -> 22962976 | D24: =SUM(D21:D23) -> 728974.63 | E24: =SUM(E21:E23) -> 320983.41 | F24: =SUM(F21:F23) -> 688268.2 | G24: =SUM(G21:G23) -> 280276.99
A26: {=_xlfn._LONGTEXT("Definitions: Net identified costout = the signed total of Column J across Licensing, Consumption, New Spend and Microsoft. Gross positive costout = positive Column J only. Finalised positive costout = positive Column J where Finalised? is Y. Budget varian","ce / reclassification = the absolute value of negative Column J. Entered renewal price sums values currently populated in Column I. Data note: ")&SUMPRODUCT(--ISNUMBER(MATCH('Fake Simplified View'!$D$2:$D$143,{"Licensing","Consumption","New spend","Microsoft"},0)),--('Fake Simplified View'!$G$2:$G$143=""))&" tracked renewal-price cells are blank, covering "&TEXT(SUMPRODUCT(--ISNUMBER(MATCH('Fake Simplified View'!$D$2:$D$143,{"Licensing","Consumption","New spend","Microsoft"},0)),--('Fake Simplified View'!$G$2:$G$143=""),'Fake Simplified View'!$F$2:$F$143),"$#,##0")&" of V1 budget."} -> Definitions: Net identified costout = the signed total of Column J across Licensing, Consumption, New Spend and Microsoft. Gross positive costout = positive Column J only. Finalised positive costout = positive Column J where Finalised? is Y. Budget variance / reclassification = the absolute value of negative Column J. Entered renewal price sums values currently populated in Column I. Data note: 8 tracked renewal-price cells are blank, covering $91,963 of V1 budget.
A30: Licensing cost-out to date
A31: {=_xlfn.LET(_xlpm.committed,_xlfn._xlws.FILTER(_xlfn.CHOOSECOLS('Fake Simplified View'!A2:H143,1,2,6,7,8),('Fake Simplified View'!D2:D143="Licensing")*(UPPER(TRIM('Fake Simplified View'!C2:C143))="Y"),""),_xlpm.committed6,_xlfn.HSTACK(_xlpm.committed,_xlfn.MAKEARRAY(ROWS(_xlpm.committed),1,_xlfn.LAMBDA(_xlpm.r,_xlpm.c,""))),_xlpm.raw,_xlfn._xlws.FILTER(_xlfn.CHOOSECOLS('Fake Simplified View'!A2:H143,1,2,5,6,7,8),('Fake Simplified View'!D2:D143="Licensing")*(UPPER(TRIM('Fake Simplified View'!C2:C143))<>"Y")),_xlpm.dates,_xlfn.CHOOSECOLS(_xlpm.raw,3),_xlpm.licensing,_xlfn.HSTACK(_xlfn.CHOOSECOLS(_xlpm.raw,1,2),IF(ISNUMBER(_xlpm.dates),IF(_xlpm.dates=0,"",TEXT(_xlpm.dates,"dd-mmm-yy")),_xlpm.dates),_xlfn.CHOOSECOLS(_xlpm.raw,4,5,6)),_xlpm.sortedLicensing,_xlfn.SORTBY(_xlpm.licensing,IF(ISNUMBER(_xlpm.dates),IF(_xlpm.dates>0,_xlpm.dates,1E+99),1E+99),1),_xlfn.VSTACK({"Vendor","Contract","V1 budget","Renewal price","Costout",""},_xlpm.committed6,{"","","","","",""},{"","","","","",""},{"Upcoming licensing vendors","","","","",""},{"Vendor","Contract","Contract date","V1 budget","Renewal price","Costout"},_xlpm.sortedLicensing))} -> Vendor | B31: Contract | C31: V1 budget | D31: Renewal price | E31: Costout | G31: {=_xlfn.LET(_xlpm.cm,('Fake Simplified View'!D2:D143="Licensing")*(UPPER(TRIM('Fake Simplified View'!C2:C143))="Y"),_xlpm.lm,('Fake Simplified View'!D2:D143="Licensing")*(UPPER(TRIM('Fake Simplified View'!C2:C143))<>"Y"),_xlpm.cc,SUM(--_xlpm.cm),_xlpm.lc,SUM(--_xlpm.lm),_xlfn.VSTACK(_xlfn.HSTACK("Committed summary","V1 budget","Renewal price","Costout"),_xlfn.HSTACK(_xlpm.cc&" committed items",SUM(_xlfn._xlws.FILTER('Fake Simplified View'!F2:F143,_xlpm.cm,0)),SUM(_xlfn._xlws.FILTER('Fake Simplified View'!G2:G143,_xlpm.cm,0)),SUM(_xlfn._xlws.FILTER('Fake Simplified View'!H2:H143,_xlpm.cm,0))),_xlfn.MAKEARRAY(_xlpm.cc+2,4,_xlfn.LAMBDA(_xlpm.r,_xlpm.c,"")),_xlfn.HSTACK("Licensing summary","V1 budget","Renewal price","Costout"),_xlfn.HSTACK(_xlpm.lc&" uncommitted items",SUM(_xlfn._xlws.FILTER('Fake Simplified View'!F2:F143,_xlpm.lm,0)),SUM(_xlfn._xlws.FILTER('Fake Simplified View'!G2:G143,_xlpm.lm,0)),SUM(_xlfn._xlws.FILTER('Fake Simplified View'!H2:H143,_xlpm.lm,0)))))} -> Committed summary | H31: V1 budget | I31: Renewal price | J31: Costout
A32: Example Vendor 001 | B32: Example Contract 001 | C32: 31644 | D32: 0 | E32: 31644 | G32: 12 committed items | H32: 342506.41 | I32: 21523 | J32: 320983.41
A33: Example Vendor 002 | B33: Example Contract 002 | C33: 33330.362 | D33: 0 | E33: 33330.362
A34: Example Vendor 003 | B34: Example Contract 003 | C34: 13440 | D34: 0 | E34: 13440
A35: Example Vendor 004 | B35: Example Contract 004 | C35: 588 | D35: 0 | E35: 588
A36: Example Vendor 006 | B36: Example Contract 006 | C36: 187065.6 | D36: 0 | E36: 187065.6
A37: Example Vendor 007 | B37: Example Contract 007 | C37: 5000 | D37: 0 | E37: 5000
A38: Example Vendor 008 | B38: Example Contract 008 | C38: 2.8456501 | D38: 0 | E38: 2.8456501
A39: Example Vendor 009 | B39: Example Contract 009 | C39: 44383.56 | D39: 21315 | E39: 23068.56
A40: Example Vendor 010 | B40: Example Contract 010 | C40: 4748.9171 | D40: 0 | E40: 4748.9171
A41: Example Vendor 027 | B41: Example Contract 038 | C41: 300.42 | D41: 208 | E41: 92.42
A42: Example Vendor 036 | B42: Example Contract 039 | C42: 12400.71 | D42: 0 | E42: 12400.71
A43: Example Vendor 032 | B43: Example Contract 042 | C43: 9602 | D43: 0 | E43: 9602
A46: Upcoming licensing vendors
A47: Vendor | B47: Contract | C47: Contract date | D47: V1 budget | E47: Renewal price | F47: Costout | G47: Licensing summary | H47: V1 budget | I47: Renewal price | J47: Costout
A48: Example Vendor 011 | B48: Example Contract 011 | C48: 31-Jul-26 | D48: 16835.05 | E48: 0 | F48: 16835.05 | G48: 95 uncommitted items | H48: 15231539 | I48: 14823392 | J48: 407591.21
A49: Example Vendor 014 | B49: Example Contract 014 | C49: 31-Jul-26 | D49: 18158.9 | E49: 13921 | F49: 4237.9
A50: Example Vendor 015 | B50: Example Contract 015 | C50: 06-Aug-26 | D50: 10897.62 | E50: 10897.62 | F50: 0
A51: Example Vendor 016 | B51: Example Contract 016 | C51: 07-Aug-26 | D51: 354869.79 | E51: 166469 | F51: 188400.79
A52: Example Vendor 017 | B52: Example Contract 017 | C52: 21-Aug-26 | D52: 145598 | E52: 141000 | F52: 4598
A53: Example Vendor 020 | B53: Example Contract 020 | C53: 30-Aug-26 | D53: 89342.25 | E53: 81676 | F53: 7666.25
A54: Example Vendor 021 | B54: Example Contract 021 | C54: 31-Aug-26 | D54: 21602.37 | E54: 16705 | F54: 4897.37
A55: Example Vendor 025 | B55: Example Contract 025 | C55: 08-Sep-26 | D55: 6959.34 | E55: 6959.34 | F55: 0
A56: Example Vendor 026 | B56: Example Contract 026 | C56: 11-Sep-26 | D56: 4000 | E56: 3928.96 | F56: 71.04
A57: Example Vendor 027 | B57: Example Contract 027 | C57: 12-Sep-26 | D57: 3496.56 | E57: 0 | F57: 3496.56
A58: Example Vendor 027 | B58: Example Contract 028 | C58: 12-Sep-26 | D58: 16764.09 | E58: 16764.09 | F58: 0
A59: Example Vendor 027 | B59: Example Contract 030 | C59: 12-Sep-26 | D59: 20822.12 | E59: 20822.12 | F59: 0
A60: Example Vendor 029 | B60: Example Contract 031 | C60: 30-Sep-26 | D60: 2116 | E60: 1709 | F60: 407
... A116: Example Vendor 102 | B116: Example Contract 137 | C116: 30-Jun-27 | D116: 20000 | E116: 60752 | F116: -40752
A117: Example Vendor 027 | B117: Example Contract 040 | C117: 0 | D117: 9951.694 | E117: 0 | F117: 9951.694
A118: Example Vendor 027 | B118: Example Contract 041 | C118: 0 | D118: 5359.7358 | E118: 0 | F118: 5359.7358
A119: Example Vendor 026 | B119: Example Contract 066 | C119: 0 | D119: 113148 | E119: 113148 | F119: 0
A120: Example Vendor 026 | B120: Example Contract 067 | C120: 0 | D120: 66087.33 | E120: 66087.33 | F120: 0
A121: Example Vendor 026 | B121: Example Contract 068 | C121: 0 | D121: 105300 | E121: 105300 | F121: 0
A122: Example Vendor 026 | B122: Example Contract 069 | C122: 0 | D122: 32601.6 | E122: 32601.6 | F122: 0
A123: Example Vendor 026 | B123: Example Contract 070 | C123: 0 | D123: 93340.8 | E123: 93340.8 | F123: 0
A124: Example Vendor 026 | B124: Example Contract 071 | C124: 0 | D124: 0 | E124: 0 | F124: 0
A125: Example Vendor 070 | B125: Example Contract 090 | C125: 0 | D125: 243750 | E125: 0 | F125: 243750
A126: Example Vendor 070 | B126: Example Contract 091 | C126: 0 | D126: 121394.16 | E126: 121394.16 | F126: 0
A127: Example Vendor 070 | B127: Example Contract 092 | C127: 0 | D127: 302982.02 | E127: 302982.02 | F127: -0.0035616438
A128: Example Vendor 070 | B128: Example Contract 093 | C128: 0 | D128: 2052892.6 | E128: 2052892.6 | F128: 0.0020547947
... A142: Example Vendor 107 | B142: Example Contract 142 | C142: 0 | D142: 172.5 | E142: 172.5 | F142: 0
A146: Consumption cost-out to date
A147: {=_xlfn.LET(_xlpm.cm,('Fake Simplified View'!D2:D143="Consumption")*(UPPER(TRIM('Fake Simplified View'!C2:C143))="Y"),_xlpm.um,('Fake Simplified View'!D2:D143="Consumption")*(UPPER(TRIM('Fake Simplified View'!C2:C143))<>"Y"),_xlpm.cc,SUM(--_xlpm.cm),_xlpm.uc,SUM(--_xlpm.um),_xlpm.committed,IF(_xlpm.cc=0,_xlfn.HSTACK("No committed consumption items","","","",""),_xlfn.LET(_xlpm.r,_xlfn._xlws.FILTER(_xlfn.CHOOSECOLS('Fake Simplified View'!A2:H143,1,2,6,7,8),_xlpm.cm),_xlfn.HSTACK(_xlfn.CHOOSECOLS(_xlpm.r,1),IF(_xlfn.CHOOSECOLS(_xlpm.r,2)=0,"",_xlfn.CHOOSECOLS(_xlpm.r,2)),_xlfn.CHOOSECOLS(_xlpm.r,3,4,5)))),_xlpm.upcoming,IF(_xlpm.uc=0,_xlfn.HSTACK("No upcoming consumption items","","","",""),_xlfn.LET(_xlpm.r,_xlfn._xlws.FILTER(_xlfn.CHOOSECOLS('Fake Simplified View'!A2:H143,1,2,6,7,8),_xlpm.um),_xlfn.HSTACK(_xlfn.CHOOSECOLS(_xlpm.r,1),IF(_xlfn.CHOOSECOLS(_xlpm.r,2)=0,"",_xlfn.CHOOSECOLS(_xlpm.r,2)),_xlfn.CHOOSECOLS(_xlpm.r,3,4,5)))),_xlfn.VSTACK(_xlfn.HSTACK("Vendor","Contract","V1 budget","Renewal price","Costout"),_xlpm.committed,_xlfn.HSTACK("","","","",""),_xlfn.HSTACK("","","","",""),_xlfn.HSTACK("Upcoming consumption vendors","","","",""),_xlfn.HSTACK("Vendor","Contract","V1 budget","Renewal price","Costout"),_xlpm.upcoming))} -> Vendor | B147: Contract | C147: V1 budget | D147: Renewal price | E147: Costout | G147: {=_xlfn.LET(_xlpm.cm,('Fake Simplified View'!D2:D143="Consumption")*(UPPER(TRIM('Fake Simplified View'!C2:C143))="Y"),_xlpm.um,('Fake Simplified View'!D2:D143="Consumption")*(UPPER(TRIM('Fake Simplified View'!C2:C143))<>"Y"),_xlpm.cc,SUM(--_xlpm.cm),_xlpm.uc,SUM(--_xlpm.um),_xlpm.displayRows,MAX(1,_xlpm.cc),_xlfn.VSTACK(_xlfn.HSTACK("Committed summary","V1 budget","Renewal price","Costout"),_xlfn.HSTACK(_xlpm.cc&" committed items",SUM(_xlfn._xlws.FILTER('Fake Simplified View'!F2:F143,_xlpm.cm,0)),SUM(_xlfn._xlws.FILTER('Fake Simplified View'!G2:G143,_xlpm.cm,0)),SUM(_xlfn._xlws.FILTER('Fake Simplified View'!H2:H143,_xlpm.cm,0))),_xlfn.MAKEARRAY(_xlpm.displayRows+2,4,_xlfn.LAMBDA(_xlpm.r,_xlpm.c,"")),_xlfn.HSTACK("Upcoming summary","V1 budget","Renewal price","Costout"),_xlfn.HSTACK(_xlpm.uc&" uncommitted items",SUM(_xlfn._xlws.FILTER('Fake Simplified View'!F2:F143,_xlpm.um,0)),SUM(_xlfn._xlws.FILTER('Fake Simplified View'!G2:G143,_xlpm.um,0)),SUM(_xlfn._xlws.FILTER('Fake Simplified View'!H2:H143,_xlpm.um,0)))))} -> Committed summary | H147: V1 budget | I147: Renewal price | J147: Costout
A148: No committed consumption items | G148: 0 committed items | H148: 0 | I148: 0 | J148: 0
A151: Upcoming consumption vendors
A152: Vendor | B152: Contract | C152: V1 budget | D152: Renewal price | E152: Costout | G152: Upcoming summary | H152: V1 budget | I152: Renewal price | J152: Costout
A153: Example Vendor 005 | B153: Example Contract 005 | C153: 5687336 | D153: 5687336 | E153: 0 | G153: 25 uncommitted items | H153: 7659712.8 | I153: 7659312.8 | J153: 400.00259
A154: Example Vendor 012 | B154: Example Contract 012 | C154: 302217 | D154: 302217 | E154: 0
A155: Example Vendor 013 | B155: Example Contract 013 | C155: 3630 | D155: 3630 | E155: 0
A156: Example Vendor 018 | B156: Example Contract 018 | C156: 9600 | D156: 9600 | E156: 0
A157: Example Vendor 019 | B157: Example Contract 019 | C157: 15000 | D157: 15000 | E157: 0
A158: Example Vendor 022 | B158: Example Contract 022 | C158: 31886.843 | D158: 31886.84 | E158: 0.0025893751
A159: Example Vendor 023 | B159: Example Contract 023 | C159: 497 | D159: 497 | E159: 0
A160: Example Vendor 024 | B160: Example Contract 024 | C160: 0 | D160: 0 | E160: 0
A161: Example Vendor 028 | B161: Example Contract 029 | C161: 973271.2 | D161: 973271.2 | E161: 0
A162: Example Vendor 049 | B162: Example Contract 055 | C162: 24000 | D162: 24000 | E162: 0
A163: Example Vendor 049 | B163: Example Contract 056 | C163: 2000 | D163: 2000 | E163: 0
A164: Example Vendor 051 | B164: Example Contract 058 | C164: 3024 | D164: 3024 | E164: 0
A165: Example Vendor 052 | B165: Example Contract 059 | C165: 14000 | D165: 14000 | E165: 0
... A177: Example Vendor 105 | B177: Example Contract 140 | C177: 400 | D177: 0 | E177: 400
A179: New Spend cost-out to date
A180: {=_xlfn.LET(_xlpm.cm,('Fake Simplified View'!D2:D143="New Spend")*(UPPER(TRIM('Fake Simplified View'!C2:C143))="Y"),_xlpm.um,('Fake Simplified View'!D2:D143="New Spend")*(UPPER(TRIM('Fake Simplified View'!C2:C143))<>"Y"),_xlpm.cc,SUM(--_xlpm.cm),_xlpm.uc,SUM(--_xlpm.um),_xlpm.committed,IF(_xlpm.cc=0,_xlfn.HSTACK("No committed new spend items","","","",""),_xlfn.LET(_xlpm.r,_xlfn._xlws.FILTER(_xlfn.CHOOSECOLS('Fake Simplified View'!A2:H143,1,2,6,7,8),_xlpm.cm),_xlfn.HSTACK(_xlfn.CHOOSECOLS(_xlpm.r,1),IF(_xlfn.CHOOSECOLS(_xlpm.r,2)=0,"",_xlfn.CHOOSECOLS(_xlpm.r,2)),_xlfn.CHOOSECOLS(_xlpm.r,3,4,5)))),_xlpm.upcoming,IF(_xlpm.uc=0,_xlfn.HSTACK("No upcoming new spend items","","","",""),_xlfn.LET(_xlpm.r,_xlfn._xlws.FILTER(_xlfn.CHOOSECOLS('Fake Simplified View'!A2:H143,1,2,6,7,8),_xlpm.um),_xlfn.HSTACK(_xlfn.CHOOSECOLS(_xlpm.r,1),IF(_xlfn.CHOOSECOLS(_xlpm.r,2)=0,"",_xlfn.CHOOSECOLS(_xlpm.r,2)),_xlfn.CHOOSECOLS(_xlpm.r,3,4,5)))),_xlfn.VSTACK(_xlfn.HSTACK("Vendor","Contract","V1 budget","Renewal price","Costout"),_xlpm.committed,_xlfn.HSTACK("","","","",""),_xlfn.HSTACK("","","","",""),_xlfn.HSTACK("Upcoming new spend vendors","","","",""),_xlfn.HSTACK("Vendor","Contract","V1 budget","Renewal price","Costout"),_xlpm.upcoming))} -> Vendor | B180: Contract | C180: V1 budget | D180: Renewal price | E180: Costout | G180: {=_xlfn.LET(_xlpm.cm,('Fake Simplified View'!D2:D143="New Spend")*(UPPER(TRIM('Fake Simplified View'!C2:C143))="Y"),_xlpm.um,('Fake Simplified View'!D2:D143="New Spend")*(UPPER(TRIM('Fake Simplified View'!C2:C143))<>"Y"),_xlpm.cc,SUM(--_xlpm.cm),_xlpm.uc,SUM(--_xlpm.um),_xlpm.displayRows,MAX(1,_xlpm.cc),_xlfn.VSTACK(_xlfn.HSTACK("Committed summary","V1 budget","Renewal price","Costout"),_xlfn.HSTACK(_xlpm.cc&" committed items",ROUND(SUM(_xlfn._xlws.FILTER('Fake Simplified View'!F2:F143,_xlpm.cm,0)),2),ROUND(SUM(_xlfn._xlws.FILTER('Fake Simplified View'!G2:G143,_xlpm.cm,0)),2),ROUND(SUM(_xlfn._xlws.FILTER('Fake Simplified View'!H2:H143,_xlpm.cm,0)),2)),_xlfn.MAKEARRAY(_xlpm.displayRows+2,4,_xlfn.LAMBDA(_xlpm.r,_xlpm.c,"")),_xlfn.HSTACK("Upcoming summary","V1 budget","Renewal price","Costout"),_xlfn.HSTACK(_xlpm.uc&" uncommitted items",ROUND(SUM(_xlfn._xlws.FILTER('Fake Simplified View'!F2:F143,_xlpm.um,0)),2),ROUND(SUM(_xlfn._xlws.FILTER('Fake Simplified View'!G2:G143,_xlpm.um,0)),2),ROUND(SUM(_xlfn._xlws.FILTER('Fake Simplified View'!H2:H143,_xlpm.um,0)),2))))} -> Committed summary | H180: V1 budget | I180: Renewal price | J180: Costout
A181: No committed new spend items | G181: 0 committed items | H181: 0 | I181: 0 | J181: 0
A184: Upcoming new spend vendors
A185: Vendor | B185: Contract | C185: V1 budget | D185: Renewal price | E185: Costout | G185: Upcoming summary | H185: V1 budget | I185: Renewal price | J185: Costout
A186: Example Vendor 030 | B186: Example Contract 032 | C186: 100000 | D186: 100000 | E186: 0 | G186: 10 uncommitted items | H186: 458748.67 | I186: 458748.67 | J186: 0
A187: Example Vendor 041 | B187: Example Contract 047 | C187: 7830 | D187: 7830 | E187: 0
A188: Example Vendor 050 | B188: Example Contract 057 | C188: 875 | D188: 875 | E188: 0
A189: Example Vendor 065 | B189: Example Contract 085 | C189: 10000 | D189: 10000 | E189: 0
A190: Example Vendor 074 | B190: Example Contract 106 | C190: 1377 | D190: 1377 | E190: 0
A191: Example Vendor 075 | B191: Example Contract 107 | C191: 80000 | D191: 80000 | E191: 0
A192: Example Vendor 076 | B192: Example Contract 108 | C192: 2000 | D192: 2000 | E192: 0
A193: Example Vendor 080 | B193: Example Contract 113 | C193: 50000 | D193: 50000 | E193: 0
A194: Example Vendor 088 | B194: Example Contract 121 | C194: 186666.67 | D194: 186666.67 | E194: 0
A195: Example Vendor 093 | B195: Example Contract 126 | C195: 20000 | D195: 20000 | E195: 0

Sheet Snapshot Wk 1
A1: IT Simplification — FY27 Cost-out Dashboard
A2: Actual savings achieved, remaining opportunity and timing by quarter
A4: V1 BUDGET | D4: ENTERED RENEWAL PRICE | G4: NET IDENTIFIED COSTOUT | I4: FINALISED POSITIVE COSTOUT
A5: 23692506 | D5: 22962976 | G5: 728974.63 | I5: 320983.41
A7: The tracked V1 budget is $23,692,506 and entered renewal prices total $22,962,976. The signed net identified costout in Column J is $728,975. Of the $1,009,252 gross positive costout identified, $320,983 is finalised (31.8%); $280,277 is separately classified as budget variance / reclassification.
A10: QUARTERLY BUDGET, RENEWAL AND COSTOUT OUTLOOK
A11: Metric | B11: Q1 FY27 | C11: Q2 FY27 | D11: Q3 FY27 | E11: Q4 FY27 | F11: Unscheduled | G11: FY27 Total
A12: V1 budget | B12: 844008.17 | C12: 3477136.3 | D12: 1175842.5 | E12: 1272025.9 | F12: 16923494 | G12: 23692506
A13: Entered renewal price | B13: 588167.13 | C13: 3379516.7 | D13: 1172578.4 | E13: 1264749.7 | F13: 16557964 | G13: 22962976
A14: Net identified costout | B14: 255841.04 | C14: 97619.637 | D14: 2708.36 | E14: 7276.18 | F14: 365529.41 | G14: 728974.63
A15: Finalised positive costout | B15: 27820.323 | C15: 22095.13 | D15: 0 | E15: 0 | F15: 271067.96 | G15: 320983.41
A16: Unfinalised positive costout | B16: 230609.96 | C16: 111226.91 | D16: 3088.36 | E16: 48881.52 | F16: 294461.45 | G16: 688268.2
A17: Budget variance / reclassification | B17: 2589.24 | C17: 35702.4 | D17: 380 | E17: 41605.34 | F17: 200000.01 | G17: 280276.99
A19: CATEGORY BUDGET, RENEWAL AND COSTOUT OUTLOOK
A20: Category | B20: V1 budget | C20: Entered renewal price | D20: Net identified costout | E20: Finalised positive costout | F20: Unfinalised positive costout | G20: Budget variance / reclassification
A21: Licensing | B21: 15574045 | C21: 14844915 | D21: 728574.63 | E21: 320983.41 | F21: 687868.2 | G21: 280276.99 | I21: Net identified costout: Overall expected reduction based on all values currently entered
A22: Consumption | B22: 7659712.8 | C22: 7659312.8 | D22: 400.00259 | E22: 0 | F22: 400.00259 | G22: 0 | I22: Finalised positive costout: Savings confirmed/completed
A23: New Spend | B23: 458748.67 | C23: 458748.67 | D23: 0 | E23: 0 | F23: 0 | G23: 0 | I23: Unfinalised positive costout: Savings pipeline - not guaranteed savings
A24: Total | B24: 23692506 | C24: 22962976 | D24: 728974.63 | E24: 320983.41 | F24: 688268.2 | G24: 280276.99
A26: Definitions: Net identified costout = the signed total of Column J across Licensing, Consumption, New Spend and Microsoft. Gross positive costout = positive Column J only. Finalised positive costout = positive Column J where Finalised? is Y. Budget variance / reclassification = the absolute value of negative Column J. Entered renewal price sums values currently populated in Column I. Data note: 8 tracked renewal-price cells are blank, covering $91,963 of V1 budget.
A30: Licensing cost-out to date
A31: Vendor | B31: Contract | C31: V1 budget | D31: Renewal price | E31: Costout | G31: Committed summary | H31: V1 budget | I31: Renewal price | J31: Costout
A32: Example Vendor 001 | B32: Example Contract 001 | C32: 31644 | D32: 0 | E32: 31644 | G32: 12 committed items | H32: 342506.41 | I32: 21523 | J32: 320983.41
A33: Example Vendor 002 | B33: Example Contract 002 | C33: 33330.362 | D33: 0 | E33: 33330.362
A34: Example Vendor 003 | B34: Example Contract 003 | C34: 13440 | D34: 0 | E34: 13440
A35: Example Vendor 004 | B35: Example Contract 004 | C35: 588 | D35: 0 | E35: 588
A36: Example Vendor 006 | B36: Example Contract 006 | C36: 187065.6 | D36: 0 | E36: 187065.6
A37: Example Vendor 007 | B37: Example Contract 007 | C37: 5000 | D37: 0 | E37: 5000
A38: Example Vendor 008 | B38: Example Contract 008 | C38: 2.8456501 | D38: 0 | E38: 2.8456501
A39: Example Vendor 009 | B39: Example Contract 009 | C39: 44383.56 | D39: 21315 | E39: 23068.56
A40: Example Vendor 010 | B40: Example Contract 010 | C40: 4748.9171 | D40: 0 | E40: 4748.9171
A41: Example Vendor 027 | B41: Example Contract 038 | C41: 300.42 | D41: 208 | E41: 92.42
A42: Example Vendor 036 | B42: Example Contract 039 | C42: 12400.71 | D42: 0 | E42: 12400.71
A43: Example Vendor 032 | B43: Example Contract 042 | C43: 9602 | D43: 0 | E43: 9602
A46: Upcoming licensing vendors
A47: Vendor | B47: Contract | C47: Contract date | D47: V1 budget | E47: Renewal price | F47: Costout | G47: Licensing summary | H47: V1 budget | I47: Renewal price | J47: Costout
A48: Example Vendor 011 | B48: Example Contract 011 | C48: 31-Jul-26 | D48: 16835.05 | E48: 0 | F48: 16835.05 | G48: 95 uncommitted items | H48: 15231539 | I48: 14823392 | J48: 407591.21
A49: Example Vendor 014 | B49: Example Contract 014 | C49: 31-Jul-26 | D49: 18158.9 | E49: 13921 | F49: 4237.9
A50: Example Vendor 015 | B50: Example Contract 015 | C50: 06-Aug-26 | D50: 10897.62 | E50: 10897.62 | F50: 0
A51: Example Vendor 016 | B51: Example Contract 016 | C51: 07-Aug-26 | D51: 354869.79 | E51: 166469 | F51: 188400.79
A52: Example Vendor 017 | B52: Example Contract 017 | C52: 21-Aug-26 | D52: 145598 | E52: 141000 | F52: 4598
A53: Example Vendor 020 | B53: Example Contract 020 | C53: 30-Aug-26 | D53: 89342.25 | E53: 81676 | F53: 7666.25
A54: Example Vendor 021 | B54: Example Contract 021 | C54: 31-Aug-26 | D54: 21602.37 | E54: 16705 | F54: 4897.37
A55: Example Vendor 025 | B55: Example Contract 025 | C55: 08-Sep-26 | D55: 6959.34 | E55: 6959.34 | F55: 0
A56: Example Vendor 026 | B56: Example Contract 026 | C56: 11-Sep-26 | D56: 4000 | E56: 3928.96 | F56: 71.04
A57: Example Vendor 027 | B57: Example Contract 027 | C57: 12-Sep-26 | D57: 3496.56 | E57: 0 | F57: 3496.56
A58: Example Vendor 027 | B58: Example Contract 028 | C58: 12-Sep-26 | D58: 16764.09 | E58: 16764.09 | F58: 0
A59: Example Vendor 027 | B59: Example Contract 030 | C59: 12-Sep-26 | D59: 20822.12 | E59: 20822.12 | F59: 0
A60: Example Vendor 029 | B60: Example Contract 031 | C60: 30-Sep-26 | D60: 2116 | E60: 1709 | F60: 407
... A116: Example Vendor 102 | B116: Example Contract 137 | C116: 30-Jun-27 | D116: 20000 | E116: 60752 | F116: -40752
A117: Example Vendor 027 | B117: Example Contract 040 | C117: 0 | D117: 9951.694 | E117: 0 | F117: 9951.694
A118: Example Vendor 027 | B118: Example Contract 041 | C118: 0 | D118: 5359.7358 | E118: 0 | F118: 5359.7358
A119: Example Vendor 026 | B119: Example Contract 066 | C119: 0 | D119: 113148 | E119: 113148 | F119: 0
A120: Example Vendor 026 | B120: Example Contract 067 | C120: 0 | D120: 66087.33 | E120: 66087.33 | F120: 0
A121: Example Vendor 026 | B121: Example Contract 068 | C121: 0 | D121: 105300 | E121: 105300 | F121: 0
A122: Example Vendor 026 | B122: Example Contract 069 | C122: 0 | D122: 32601.6 | E122: 32601.6 | F122: 0
A123: Example Vendor 026 | B123: Example Contract 070 | C123: 0 | D123: 93340.8 | E123: 93340.8 | F123: 0
A124: Example Vendor 026 | B124: Example Contract 071 | C124: 0 | D124: 0 | E124: 0 | F124: 0
A125: Example Vendor 070 | B125: Example Contract 090 | C125: 0 | D125: 243750 | E125: 0 | F125: 243750
A126: Example Vendor 070 | B126: Example Contract 091 | C126: 0 | D126: 121394.16 | E126: 121394.16 | F126: 0
A127: Example Vendor 070 | B127: Example Contract 092 | C127: 0 | D127: 302982.02 | E127: 302982.02 | F127: -0.0035616438
A128: Example Vendor 070 | B128: Example Contract 093 | C128: 0 | D128: 2052892.6 | E128: 2052892.6 | F128: 0.0020547947
... A142: Example Vendor 107 | B142: Example Contract 142 | C142: 0 | D142: 172.5 | E142: 172.5 | F142: 0
A146: Consumption cost-out to date
A147: Vendor | B147: Contract | C147: V1 budget | D147: Renewal price | E147: Costout | G147: Committed summary | H147: V1 budget | I147: Renewal price | J147: Costout
A148: No committed consumption items | G148: 0 committed items | H148: 0 | I148: 0 | J148: 0
A151: Upcoming consumption vendors
A152: Vendor | B152: Contract | C152: V1 budget | D152: Renewal price | E152: Costout | G152: Upcoming summary | H152: V1 budget | I152: Renewal price | J152: Costout
A153: Example Vendor 005 | B153: Example Contract 005 | C153: 5687336 | D153: 5687336 | E153: 0 | G153: 25 uncommitted items | H153: 7659712.8 | I153: 7659312.8 | J153: 400.00259
A154: Example Vendor 012 | B154: Example Contract 012 | C154: 302217 | D154: 302217 | E154: 0
A155: Example Vendor 013 | B155: Example Contract 013 | C155: 3630 | D155: 3630 | E155: 0
A156: Example Vendor 018 | B156: Example Contract 018 | C156: 9600 | D156: 9600 | E156: 0
A157: Example Vendor 019 | B157: Example Contract 019 | C157: 15000 | D157: 15000 | E157: 0
A158: Example Vendor 022 | B158: Example Contract 022 | C158: 31886.843 | D158: 31886.84 | E158: 0.0025893751
A159: Example Vendor 023 | B159: Example Contract 023 | C159: 497 | D159: 497 | E159: 0
A160: Example Vendor 024 | B160: Example Contract 024 | C160: 0 | D160: 0 | E160: 0
A161: Example Vendor 028 | B161: Example Contract 029 | C161: 973271.2 | D161: 973271.2 | E161: 0
A162: Example Vendor 049 | B162: Example Contract 055 | C162: 24000 | D162: 24000 | E162: 0
A163: Example Vendor 049 | B163: Example Contract 056 | C163: 2000 | D163: 2000 | E163: 0
A164: Example Vendor 051 | B164: Example Contract 058 | C164: 3024 | D164: 3024 | E164: 0
A165: Example Vendor 052 | B165: Example Contract 059 | C165: 14000 | D165: 14000 | E165: 0
... A177: Example Vendor 105 | B177: Example Contract 140 | C177: 400 | D177: 0 | E177: 400
A179: New Spend cost-out to date
A180: Vendor | B180: Contract | C180: V1 budget | D180: Renewal price | E180: Costout | G180: Committed summary | H180: V1 budget | I180: Renewal price | J180: Costout
A181: No committed new spend items | G181: 0 committed items | H181: 0 | I181: 0 | J181: 0
A184: Upcoming new spend vendors
A185: Vendor | B185: Contract | C185: V1 budget | D185: Renewal price | E185: Costout | G185: Upcoming summary | H185: V1 budget | I185: Renewal price | J185: Costout
A186: Example Vendor 030 | B186: Example Contract 032 | C186: 100000 | D186: 100000 | E186: 0 | G186: 10 uncommitted items | H186: 458748.67 | I186: 458748.67 | J186: 0
A187: Example Vendor 041 | B187: Example Contract 047 | C187: 7830 | D187: 7830 | E187: 0
A188: Example Vendor 050 | B188: Example Contract 057 | C188: 875 | D188: 875 | E188: 0
A189: Example Vendor 065 | B189: Example Contract 085 | C189: 10000 | D189: 10000 | E189: 0
A190: Example Vendor 074 | B190: Example Contract 106 | C190: 1377 | D190: 1377 | E190: 0
A191: Example Vendor 075 | B191: Example Contract 107 | C191: 80000 | D191: 80000 | E191: 0
A192: Example Vendor 076 | B192: Example Contract 108 | C192: 2000 | D192: 2000 | E192: 0
A193: Example Vendor 080 | B193: Example Contract 113 | C193: 50000 | D193: 50000 | E193: 0
A194: Example Vendor 088 | B194: Example Contract 121 | C194: 186666.67 | D194: 186666.67 | E194: 0
A195: Example Vendor 093 | B195: Example Contract 126 | C195: 20000 | D195: 20000 | E195: 0

Sheet Snapshot Wk 2
A1: IT Simplification — FY27 Cost-out Dashboard
A2: Actual savings achieved, remaining opportunity and timing by quarter
A4: V1 BUDGET | D4: ENTERED RENEWAL PRICE | G4: NET IDENTIFIED COSTOUT | I4: FINALISED POSITIVE COSTOUT
A5: 23692506 | D5: 22938226 | G5: 753724.72 | I5: 556024.67
A7: The tracked V1 budget is $23,692,506 and entered renewal prices total $22,938,226. The signed net identified costout in Column J is $753,725. Of the $1,028,442 gross positive costout identified, $556,025 is finalised (54.1%); $274,717 is separately classified as budget variance / reclassification.
A10: QUARTERLY BUDGET, RENEWAL AND COSTOUT OUTLOOK
A11: Metric | B11: Q1 FY27 | C11: Q2 FY27 | D11: Q3 FY27 | E11: Q4 FY27 | F11: Unscheduled | G11: FY27 Total
A12: V1 budget | B12: 844008.17 | C12: 3477136.3 | D12: 1175842.5 | E12: 1272025.9 | F12: 16923494 | G12: 23692506
A13: Entered renewal price | B13: 571403.04 | C13: 3372027.7 | D13: 1172578.4 | E13: 1264749.7 | F13: 16557467 | G13: 22938226
A14: Net identified costout | B14: 272605.13 | C14: 105108.64 | D14: 2708.36 | E14: 7276.18 | F14: 366026.41 | G14: 753724.72
A15: Finalised positive costout | B15: 254862.68 | C15: 30094.03 | D15: 0 | E15: 0 | F15: 271067.96 | G15: 556024.67
A16: Unfinalised positive costout | B16: 20331.69 | C16: 105157.01 | D16: 3088.36 | E16: 48881.52 | F16: 294958.45 | G16: 472417.03
A17: Budget variance / reclassification | B17: 2589.24 | C17: 30142.4 | D17: 380 | E17: 41605.34 | F17: 200000.01 | G17: 274716.99
A19: CATEGORY BUDGET, RENEWAL AND COSTOUT OUTLOOK
A20: Category | B20: V1 budget | C20: Entered renewal price | D20: Net identified costout | E20: Finalised positive costout | F20: Unfinalised positive costout | G20: Budget variance / reclassification
A21: Licensing | B21: 15574045 | C21: 14820661 | D21: 752827.72 | E21: 556024.67 | F21: 471520.03 | G21: 274716.99 | I21: Net identified costout: Overall expected reduction based on all values currently entered
A22: Consumption | B22: 7659712.8 | C22: 7658815.8 | D22: 897.00259 | E22: 0 | F22: 897.00259 | G22: 0 | I22: Finalised positive costout: Savings confirmed/completed
A23: New Spend | B23: 458748.67 | C23: 458748.67 | D23: 0 | E23: 0 | F23: 0 | G23: 0 | I23: Unfinalised positive costout: Savings pipeline - not guaranteed savings
A24: Total | B24: 23692506 | C24: 22938226 | D24: 753724.72 | E24: 556024.67 | F24: 472417.03 | G24: 274716.99
A26: Definitions: Net identified costout = the signed total of Column J across Licensing, Consumption, New Spend and Microsoft. Gross positive costout = positive Column J only. Finalised positive costout = positive Column J where Finalised? is Y. Budget variance / reclassification = the absolute value of negative Column J. Entered renewal price sums values currently populated in Column I. Data note: 8 tracked renewal-price cells are blank, covering $91,963 of V1 budget.
A30: Licensing cost-out to date
A31: Vendor | B31: Contract | C31: V1 budget | D31: Renewal price | E31: Costout | G31: Committed summary | H31: V1 budget | I31: Renewal price | J31: Costout
A32: Example Vendor 001 | B32: Example Contract 001 | C32: 31644 | D32: 0 | E32: 31644 | G32: 22 committed items | H32: 1053476.8 | I32: 497452.12 | J32: 556024.67
A33: Example Vendor 002 | B33: Example Contract 002 | C33: 33330.362 | D33: 0 | E33: 33330.362
A34: Example Vendor 003 | B34: Example Contract 003 | C34: 13440 | D34: 0 | E34: 13440
A35: Example Vendor 004 | B35: Example Contract 004 | C35: 588 | D35: 0 | E35: 588
A36: Example Vendor 006 | B36: Example Contract 006 | C36: 187065.6 | D36: 0 | E36: 187065.6
A37: Example Vendor 007 | B37: Example Contract 007 | C37: 5000 | D37: 0 | E37: 5000
A38: Example Vendor 008 | B38: Example Contract 008 | C38: 2.8456501 | D38: 0 | E38: 2.8456501
A39: Example Vendor 009 | B39: Example Contract 009 | C39: 44383.56 | D39: 21315 | E39: 23068.56
A40: Example Vendor 010 | B40: Example Contract 010 | C40: 4748.9171 | D40: 0 | E40: 4748.9171
A41: Example Vendor 011 | B41: Example Contract 011 | C41: 16835.05 | D41: 0 | E41: 16835.05
A42: Example Vendor 014 | B42: Example Contract 014 | C42: 18158.9 | D42: 13921 | E42: 4237.9
A43: Example Vendor 016 | B43: Example Contract 016 | C43: 354869.79 | D43: 166469 | E43: 188400.79
A44: Example Vendor 017 | B44: Example Contract 017 | C44: 145598 | D44: 141000 | E44: 4598
... A53: Example Vendor 032 | B53: Example Contract 042 | C53: 9602 | D53: 0 | E53: 9602
A56: Upcoming licensing vendors
A57: Vendor | B57: Contract | C57: Contract date | D57: V1 budget | E57: Renewal price | F57: Costout | G57: Licensing summary | H57: V1 budget | I57: Renewal price | J57: Costout
A58: Example Vendor 015 | B58: Example Contract 015 | C58: 06-Aug-26 | D58: 10897.62 | E58: 10897.62 | F58: 0 | G58: 85 uncommitted items | H58: 14520568 | I58: 14323209 | J58: 196803.04
A59: Example Vendor 025 | B59: Example Contract 025 | C59: 08-Sep-26 | D59: 6959.34 | E59: 6959.34 | F59: 0
A60: Example Vendor 026 | B60: Example Contract 026 | C60: 11-Sep-26 | D60: 4000 | E60: 3928.96 | F60: 71.04
A61: Example Vendor 027 | B61: Example Contract 027 | C61: 12-Sep-26 | D61: 3496.56 | E61: 0 | F61: 3496.56
A62: Example Vendor 027 | B62: Example Contract 028 | C62: 12-Sep-26 | D62: 16764.09 | E62: 0 | F62: 16764.09
A63: Example Vendor 031 | B63: Example Contract 033 | C63: 30-Sep-26 | D63: 83410.76 | E63: 86000 | F63: -2589.24
A64: Example Vendor 033 | B64: Example Contract 035 | C64: 03-Oct-26 | D64: 1771.24 | E64: 1771.24 | F64: 0
A65: Example Vendor 035 | B65: Example Contract 037 | C65: 09-Oct-26 | D65: 2558.56 | E65: 2558.56 | F65: 0
A66: Example Vendor 037 | B66: Example Contract 043 | C66: 02-Nov-26 | D66: 63000 | E66: 63000 | F66: 0
A67: Example Vendor 038 | B67: Example Contract 044 | C67: 14-Nov-26 | D67: 62507 | E67: 62507 | F67: 0
A68: Example Vendor 039 | B68: Example Contract 045 | C68: 28-Nov-26 | D68: 15442.02 | E68: 15442.02 | F68: 0
A69: Example Vendor 040 | B69: Example Contract 046 | C69: 29-Nov-26 | D69: 22489.93 | E69: 22489.93 | F69: 0
A70: Example Vendor 042 | B70: Example Contract 048 | C70: 30-Nov-26 | D70: 55533.21 | E70: 55533.21 | F70: 0
... A116: Example Vendor 102 | B116: Example Contract 137 | C116: 30-Jun-27 | D116: 20000 | E116: 60752 | F116: -40752
A117: Example Vendor 027 | B117: Example Contract 040 | C117: 0 | D117: 9951.694 | E117: 0 | F117: 9951.694
A118: Example Vendor 027 | B118: Example Contract 041 | C118: 0 | D118: 5359.7358 | E118: 0 | F118: 5359.7358
A119: Example Vendor 026 | B119: Example Contract 066 | C119: 0 | D119: 113148 | E119: 113148 | F119: 0
A120: Example Vendor 026 | B120: Example Contract 067 | C120: 0 | D120: 66087.33 | E120: 66087.33 | F120: 0
A121: Example Vendor 026 | B121: Example Contract 068 | C121: 0 | D121: 105300 | E121: 105300 | F121: 0
A122: Example Vendor 026 | B122: Example Contract 069 | C122: 0 | D122: 32601.6 | E122: 32601.6 | F122: 0
A123: Example Vendor 026 | B123: Example Contract 070 | C123: 0 | D123: 93340.8 | E123: 93340.8 | F123: 0
A124: Example Vendor 026 | B124: Example Contract 071 | C124: 0 | D124: 0 | E124: 0 | F124: 0
A125: Example Vendor 070 | B125: Example Contract 090 | C125: 0 | D125: 243750 | E125: 0 | F125: 243750
A126: Example Vendor 070 | B126: Example Contract 091 | C126: 0 | D126: 121394.16 | E126: 121394.16 | F126: 0
A127: Example Vendor 070 | B127: Example Contract 092 | C127: 0 | D127: 302982.02 | E127: 302982.02 | F127: -0.0035616438
A128: Example Vendor 070 | B128: Example Contract 093 | C128: 0 | D128: 2052892.6 | E128: 2052892.6 | F128: 0.0020547947
... A142: Example Vendor 107 | B142: Example Contract 142 | C142: 0 | D142: 172.5 | E142: 172.5 | F142: 0
A146: Consumption cost-out to date
A147: Vendor | B147: Contract | C147: V1 budget | D147: Renewal price | E147: Costout | G147: Committed summary | H147: V1 budget | I147: Renewal price | J147: Costout
A148: No committed consumption items | G148: 0 committed items | H148: 0 | I148: 0 | J148: 0
A151: Upcoming consumption vendors
A152: Vendor | B152: Contract | C152: V1 budget | D152: Renewal price | E152: Costout | G152: Upcoming summary | H152: V1 budget | I152: Renewal price | J152: Costout
A153: Example Vendor 005 | B153: Example Contract 005 | C153: 5687336 | D153: 5687336 | E153: 0 | G153: 25 uncommitted items | H153: 7659712.8 | I153: 7658815.8 | J153: 897.00259
A154: Example Vendor 012 | B154: Example Contract 012 | C154: 302217 | D154: 302217 | E154: 0
A155: Example Vendor 013 | B155: Example Contract 013 | C155: 3630 | D155: 3630 | E155: 0
A156: Example Vendor 018 | B156: Example Contract 018 | C156: 9600 | D156: 9600 | E156: 0
A157: Example Vendor 019 | B157: Example Contract 019 | C157: 15000 | D157: 15000 | E157: 0
A158: Example Vendor 022 | B158: Example Contract 022 | C158: 31886.843 | D158: 31886.84 | E158: 0.0025893751
A159: Example Vendor 023 | B159: Example Contract 023 | C159: 497 | D159: 0 | E159: 497
A160: Example Vendor 024 | B160: Example Contract 024 | C160: 0 | D160: 0 | E160: 0
A161: Example Vendor 028 | B161: Example Contract 029 | C161: 973271.2 | D161: 973271.2 | E161: 0
A162: Example Vendor 049 | B162: Example Contract 055 | C162: 24000 | D162: 24000 | E162: 0
A163: Example Vendor 049 | B163: Example Contract 056 | C163: 2000 | D163: 2000 | E163: 0
A164: Example Vendor 051 | B164: Example Contract 058 | C164: 3024 | D164: 3024 | E164: 0
A165: Example Vendor 052 | B165: Example Contract 059 | C165: 14000 | D165: 14000 | E165: 0
... A177: Example Vendor 105 | B177: Example Contract 140 | C177: 400 | D177: 0 | E177: 400
A179: New Spend cost-out to date
A180: Vendor | B180: Contract | C180: V1 budget | D180: Renewal price | E180: Costout | G180: Committed summary | H180: V1 budget | I180: Renewal price | J180: Costout
A181: No committed new spend items | G181: 0 committed items | H181: 0 | I181: 0 | J181: 0
A184: Upcoming new spend vendors
A185: Vendor | B185: Contract | C185: V1 budget | D185: Renewal price | E185: Costout | G185: Upcoming summary | H185: V1 budget | I185: Renewal price | J185: Costout
A186: Example Vendor 030 | B186: Example Contract 032 | C186: 100000 | D186: 100000 | E186: 0 | G186: 10 uncommitted items | H186: 458748.67 | I186: 458748.67 | J186: 0
A187: Example Vendor 041 | B187: Example Contract 047 | C187: 7830 | D187: 7830 | E187: 0
A188: Example Vendor 050 | B188: Example Contract 057 | C188: 875 | D188: 875 | E188: 0
A189: Example Vendor 065 | B189: Example Contract 085 | C189: 10000 | D189: 10000 | E189: 0
A190: Example Vendor 074 | B190: Example Contract 106 | C190: 1377 | D190: 1377 | E190: 0
A191: Example Vendor 075 | B191: Example Contract 107 | C191: 80000 | D191: 80000 | E191: 0
A192: Example Vendor 076 | B192: Example Contract 108 | C192: 2000 | D192: 2000 | E192: 0
A193: Example Vendor 080 | B193: Example Contract 113 | C193: 50000 | D193: 50000 | E193: 0
A194: Example Vendor 088 | B194: Example Contract 121 | C194: 186666.67 | D194: 186666.67 | E194: 0
A195: Example Vendor 093 | B195: Example Contract 126 | C195: 20000 | D195: 20000 | E195: 0

Sheet Fake Simplified View
A1: Vendor | B1: Contract | C1: Finalised? | D1: Category | E1: When contract is up | F1: V1 budget | G1: Renewal price | H1: Costout | I1: Status
A2: Example Vendor 001 | B2: Example Contract 001 | C2: Y | D2: Licensing | E2: 46203 | F2: 31644 | G2: 0 | H2: =F2-G2 -> 31644
A3: Example Vendor 002 | B3: Example Contract 002 | C3: Y | D3: Licensing | E3: 46203 | F3: 33330.362 | G3: 0 | H3: =F3-G3 -> 33330.362
A4: Example Vendor 003 | B4: Example Contract 003 | C4: Y | D4: Licensing | E4: 46203 | F4: 13440 | G4: 0 | H4: =F4-G4 -> 13440
A5: Example Vendor 004 | B5: Example Contract 004 | C5: Y | D5: Licensing | E5: 46203 | F5: 588 | G5: 0 | H5: =F5-G5 -> 588
A6: Example Vendor 005 | B6: Example Contract 005 | D6: Consumption | E6: NA | F6: 5687336 | G6: 5687336 | H6: =F6-G6 -> 0
A7: Example Vendor 006 | B7: Example Contract 006 | C7: Y | D7: Licensing | E7: 46203 | F7: 187065.6 | G7: 0 | H7: =F7-G7 -> 187065.6
A8: Example Vendor 007 | B8: Example Contract 007 | C8: Y | D8: Licensing | E8: 46203 | F8: 5000 | G8: 0 | H8: =F8-G8 -> 5000
A9: Example Vendor 008 | B9: Example Contract 008 | C9: Y | D9: Licensing | E9: 46206 | F9: 2.8456501 | G9: 0 | H9: =F9-G9 -> 2.8456501
A10: Example Vendor 009 | B10: Example Contract 009 | C10: Y | D10: Licensing | E10: 46223 | F10: 44383.56 | G10: 21315 | H10: =F10-G10 -> 23068.56 | I10: Example status update
A11: Example Vendor 010 | B11: Example Contract 010 | C11: Y | D11: Licensing | E11: 46230 | F11: 4748.9171 | G11: 0 | H11: =F11-G11 -> 4748.9171
A12: Example Vendor 011 | B12: Example Contract 011 | D12: Licensing | E12: 46234 | F12: 16835.05 | G12: 0 | H12: =F12-G12 -> 16835.05
A13: Example Vendor 012 | B13: Example Contract 012 | D13: Consumption | E13: NA | F13: 302217 | G13: 302217 | H13: =F13-G13 -> 0
A14: Example Vendor 013 | B14: Example Contract 013 | D14: Consumption | E14: NA | F14: 3630 | G14: 3630 | H14: =F14-G14 -> 0
A15: Example Vendor 014 | B15: Example Contract 014 | D15: Licensing | E15: 46234 | F15: 18158.9 | G15: 13921 | H15: =F15-G15 -> 4237.9
A16: Example Vendor 015 | B16: Example Contract 015 | D16: Licensing | E16: 46240 | F16: 10897.62 | G16: 10897.62 | H16: =F16-G16 -> 0
A17: Example Vendor 016 | B17: Example Contract 016 | D17: Licensing | E17: 46241 | F17: 354869.79 | G17: 166469 | H17: =F17-G17 -> 188400.79 | I17: Example status update
A18: Example Vendor 017 | B18: Example Contract 017 | D18: Licensing | E18: 46255 | F18: 145598 | G18: 141000 | H18: =F18-G18 -> 4598 | I18: Example status update
A19: Example Vendor 018 | B19: Example Contract 018 | D19: Consumption | E19: NA | F19: 9600 | G19: 9600 | H19: =F19-G19 -> 0
A20: Example Vendor 019 | B20: Example Contract 019 | D20: Consumption | E20: NA | F20: 15000 | G20: 15000 | H20: =F20-G20 -> 0
A21: Example Vendor 020 | B21: Example Contract 020 | D21: Licensing | E21: 46264 | F21: 89342.25 | G21: 81676 | H21: =F21-G21 -> 7666.25 | I21: Example status update
A22: Example Vendor 021 | B22: Example Contract 021 | D22: Licensing | E22: 46265 | F22: 21602.37 | G22: 16705 | H22: =F22-G22 -> 4897.37 | I22: Example status update
A23: Example Vendor 022 | B23: Example Contract 022 | D23: Consumption | E23: NA | F23: 31886.843 | G23: 31886.84 | H23: =F23-G23 -> 0.0025893751
A24: Example Vendor 023 | B24: Example Contract 023 | D24: Consumption | E24: NA | F24: 497 | G24: 497 | H24: =F24-G24 -> 0
A25: Example Vendor 024 | B25: Example Contract 024 | D25: Consumption | E25: NA | F25: 0 | H25: =F25-G25 -> 0
A26: Example Vendor 025 | B26: Example Contract 025 | D26: Licensing | E26: 46273 | F26: 6959.34 | G26: 6959.34 | H26: =F26-G26 -> 0 | I26: Example status update
A27: Example Vendor 026 | B27: Example Contract 026 | D27: Licensing | E27: 46276 | F27: 4000 | G27: 3928.96 | H27: =F27-G27 -> 71.04 | I27: Example status update
A28: Example Vendor 027 | B28: Example Contract 027 | D28: Licensing | E28: 46277 | F28: 3496.56 | G28: 0 | H28: =F28-G28 -> 3496.56 | I28: Example status update
A29: Example Vendor 027 | B29: Example Contract 028 | D29: Licensing | E29: 46277 | F29: 16764.09 | G29: 16764.09 | H29: =F29-G29 -> 0 | I29: Example status update
A30: Example Vendor 028 | B30: Example Contract 029 | D30: Consumption | E30: NA | F30: 973271.2 | G30: 973271.2 | H30: =F30-G30 -> 0
A31: Example Vendor 027 | B31: Example Contract 030 | D31: Licensing | E31: 46277 | F31: 20822.12 | G31: 20822.12 | H31: =F31-G31 -> 0 | I31: Example status update
A32: Example Vendor 029 | B32: Example Contract 031 | D32: Licensing | E32: 46295 | F32: 2116 | G32: 1709 | H32: =F32-G32 -> 407 | I32: Example status update
A33: Example Vendor 030 | B33: Example Contract 032 | D33: New spend | F33: 100000 | G33: 100000 | H33: =F33-G33 -> 0
A34: Example Vendor 031 | B34: Example Contract 033 | D34: Licensing | E34: 46295 | F34: 83410.76 | G34: 86000 | H34: =F34-G34 -> -2589.24 | I34: Example status update
A35: Example Vendor 032 | B35: Example Contract 034 | D35: Licensing | E35: 46297 | F35: 29440 | G35: 35000 | H35: =F35-G35 -> -5560
A36: Example Vendor 033 | B36: Example Contract 035 | D36: Licensing | E36: 46298 | F36: 1771.24 | G36: 1771.24 | H36: =F36-G36 -> 0
A37: Example Vendor 034 | B37: Example Contract 036 | D37: Licensing | E37: 46301 | F37: 12185.9 | G37: 6116 | H37: =F37-G37 -> 6069.9
A38: Example Vendor 035 | B38: Example Contract 037 | D38: Licensing | E38: 46304 | F38: 2558.56 | G38: 2558.56 | H38: =F38-G38 -> 0
A39: Example Vendor 027 | B39: Example Contract 038 | C39: Y | D39: Licensing | E39: 46306 | F39: 300.42 | G39: 208 | H39: =F39-G39 -> 92.42
A40: Example Vendor 036 | B40: Example Contract 039 | C40: Y | D40: Licensing | E40: 46319 | F40: 12400.71 | G40: 0 | H40: =F40-G40 -> 12400.71
A41: Example Vendor 027 | B41: Example Contract 040 | D41: Licensing | F41: 9951.694 | H41: =F41-G41 -> 9951.694
A42: Example Vendor 027 | B42: Example Contract 041 | D42: Licensing | F42: 5359.7358 | H42: =F42-G42 -> 5359.7358
A43: Example Vendor 032 | B43: Example Contract 042 | C43: Y | D43: Licensing | E43: 46326 | F43: 9602 | G43: 0 | H43: =F43-G43 -> 9602
A44: Example Vendor 037 | B44: Example Contract 043 | D44: Licensing | E44: 46328 | F44: 63000 | G44: 63000 | H44: =F44-G44 -> 0
A45: Example Vendor 038 | B45: Example Contract 044 | D45: Licensing | E45: 46340 | F45: 62507 | G45: 62507 | H45: =F45-G45 -> 0
A46: Example Vendor 039 | B46: Example Contract 045 | D46: Licensing | E46: 46354 | F46: 15442.02 | G46: 15442.02 | H46: =F46-G46 -> 0
A47: Example Vendor 040 | B47: Example Contract 046 | D47: Licensing | E47: 46355 | F47: 22489.93 | G47: 22489.93 | H47: =F47-G47 -> 0
A48: Example Vendor 041 | B48: Example Contract 047 | D48: New spend | F48: 7830 | G48: 7830 | H48: =F48-G48 -> 0
A49: Example Vendor 042 | B49: Example Contract 048 | D49: Licensing | E49: 46356 | F49: 55533.21 | G49: 55533.21 | H49: =F49-G49 -> 0
A50: Example Vendor 043 | B50: Example Contract 049 | D50: Licensing | E50: 46357 | F50: 44854.09 | G50: 44854.09 | H50: =F50-G50 -> 0
A51: Example Vendor 044 | B51: Example Contract 050 | D51: Licensing | E51: 46360 | F51: 0 | G51: 142.4 | H51: =F51-G51 -> -142.4
A52: Example Vendor 045 | B52: Example Contract 051 | D52: Licensing | E52: 46364 | F52: 16000 | G52: 10780.5 | H52: =F52-G52 -> 5219.5
A53: Example Vendor 046 | B53: Example Contract 052 | D53: Licensing | E53: 46364 | F53: 38169.86 | G53: 38169.86 | H53: =F53-G53 -> 0
A54: Example Vendor 047 | B54: Example Contract 053 | D54: Licensing | E54: 46368 | F54: 72737.12 | G54: 72737.12 | H54: =F54-G54 -> 0
A55: Example Vendor 048 | B55: Example Contract 054 | D55: Licensing | E55: 46371 | F55: 7767.45 | G55: 6000 | H55: =F55-G55 -> 1767.45
A56: Example Vendor 049 | B56: Example Contract 055 | D56: Consumption | E56: NA | F56: 24000 | G56: 24000 | H56: =F56-G56 -> 0
A57: Example Vendor 049 | B57: Example Contract 056 | D57: Consumption | E57: NA | F57: 2000 | G57: 2000 | H57: =F57-G57 -> 0
A58: Example Vendor 050 | B58: Example Contract 057 | D58: New spend | F58: 875 | G58: 875 | H58: =F58-G58 -> 0
A59: Example Vendor 051 | B59: Example Contract 058 | D59: Consumption | E59: NA | F59: 3024 | G59: 3024 | H59: =F59-G59 -> 0
A60: Example Vendor 052 | B60: Example Contract 059 | D60: Consumption | E60: NA | F60: 14000 | G60: 14000 | H60: =F60-G60 -> 0
A61: Example Vendor 034 | B61: Example Contract 060 | D61: Licensing | E61: 46372 | F61: 513 | G61: 513 | H61: =F61-G61 -> 0
A62: Example Vendor 053 | B62: Example Contract 061 | D62: Licensing | E62: 46373 | F62: 83640.9 | G62: 83640.9 | H62: =F62-G62 -> 0
A63: Example Vendor 054 | B63: Example Contract 062 | D63: Consumption
A64: Example Vendor 055 | B64: Example Contract 063 | D64: Licensing | E64: 46378 | F64: 819389.08 | G64: 819389.08 | H64: =F64-G64 -> 0
A65: Example Vendor 055 | B65: Example Contract 064 | D65: Licensing | E65: 46378 | F65: 114542.94 | G65: 144542.94 | H65: =F65-G65 -> -30000
A66: Example Vendor 056 | B66: Example Contract 065 | D66: Licensing | E66: 46387 | F66: 1806000 | G66: 1806000 | H66: =F66-G66 -> 0
A67: Example Vendor 026 | B67: Example Contract 066 | D67: Licensing | F67: 113148 | G67: 113148 | H67: =F67-G67 -> 0
A68: Example Vendor 026 | B68: Example Contract 067 | D68: Licensing | F68: 66087.33 | G68: 66087.33 | H68: =F68-G68 -> 0
A69: Example Vendor 026 | B69: Example Contract 068 | D69: Licensing | F69: 105300 | G69: 105300 | H69: =F69-G69 -> 0
A70: Example Vendor 026 | B70: Example Contract 069 | D70: Licensing | F70: 32601.6 | G70: 32601.6 | H70: =F70-G70 -> 0
A71: Example Vendor 026 | B71: Example Contract 070 | D71: Licensing | F71: 93340.8 | G71: 93340.8 | H71: =F71-G71 -> 0
A72: Example Vendor 026 | B72: Example Contract 071 | D72: Licensing
A73: Example Vendor 056 | B73: Example Contract 072 | D73: Licensing | E73: 46387 | F73: 76651.437 | H73: =F73-G73 -> 76651.437
A74: Example Vendor 057 | B74: Example Contract 073 | D74: Licensing | E74: 46387 | F74: 74680.82 | G74: 74680.82 | H74: =F74-G74 -> 0
A75: Example Vendor 058 | B75: Example Contract 074 | D75: Licensing | E75: 46387 | F75: 24773.62 | G75: 13440 | H75: =F75-G75 -> 11333.62
A76: Example Vendor 046 | B76: Example Contract 075 | D76: Licensing | E76: 46387 | F76: 10185 | G76: 0 | H76: =F76-G76 -> 10185
A77: Example Vendor 032 | B77: Example Contract 076 | D77: Consumption | E77: NA | F77: 40000 | G77: 40000 | H77: =F77-G77 -> 0
A78: Example Vendor 059 | B78: Example Contract 077 | D78: Licensing | E78: 46392 | F78: 836817.43 | G78: 836817.43 | H78: =F78-G78 -> 0
A79: Example Vendor 060 | B79: Example Contract 078 | D79: Licensing | E79: 46401 | F79: 43880.53 | G79: 43880.53 | H79: =F79-G79 -> 0
A80: Example Vendor 061 | B80: Example Contract 079 | D80: Licensing | E80: 46401 | F80: 678.87 | G80: 678.87 | H80: =F80-G80 -> 0
A81: Example Vendor 062 | B81: Example Contract 080 | D81: Licensing | E81: 46406 | F81: 2474.14 | G81: 2474.14 | H81: =F81-G81 -> 0
A82: Example Vendor 063 | B82: Example Contract 081 | D82: Consumption | E82: NA | F82: 296008 | G82: 296008 | H82: =F82-G82 -> 0
A83: Example Vendor 054 | B83: Example Contract 082 | D83: Licensing | E83: 46407 | F83: 0 | G83: 0 | H83: =F83-G83 -> 0
A84: Example Vendor 033 | B84: Example Contract 083 | D84: Licensing | E84: 46407 | F84: 1788.49 | G84: 1788.49 | H84: =F84-G84 -> 0
A85: Example Vendor 064 | B85: Example Contract 084 | D85: Consumption | E85: NA | F85: 20620.8 | G85: 20620.8 | H85: =F85-G85 -> 0
A86: Example Vendor 065 | B86: Example Contract 085 | D86: New spend | F86: 10000 | G86: 10000 | H86: =F86-G86 -> 0
A87: Example Vendor 066 | B87: Example Contract 086 | D87: Licensing | E87: 46408 | F87: 85828.33 | G87: 85828.33 | H87: =F87-G87 -> 0
A88: Example Vendor 067 | B88: Example Contract 087 | D88: Consumption | E88: NA | F88: 18000 | G88: 18000 | H88: =F88-G88 -> 0
A89: Example Vendor 068 | B89: Example Contract 088 | D89: Licensing | E89: 46412 | F89: 420 | G89: 179.50685 | H89: 0
A90: Example Vendor 069 | B90: Example Contract 089 | D90: Licensing | E90: 46440 | F90: 8702 | G90: 8702 | H90: =F90-G90 -> 0
A91: Example Vendor 070 | B91: Example Contract 090 | D91: Licensing | F91: 243750 | G91: 0 | H91: =F91-G91 -> 243750
A92: Example Vendor 070 | B92: Example Contract 091 | D92: Licensing | F92: 121394.16 | G92: 121394.16 | H92: =F92-G92 -> 0
A93: Example Vendor 070 | B93: Example Contract 092 | D93: Licensing | F93: 302982.02 | G93: 302982.02 | H93: =F93-G93 -> -0.0035616438
A94: Example Vendor 070 | B94: Example Contract 093 | D94: Licensing | F94: 2052892.6 | G94: 2052892.6 | H94: =F94-G94 -> 0.0020547947
A95: Example Vendor 070 | B95: Example Contract 094 | D95: Licensing | F95: 4790082.8 | G95: 4790082.8 | H95: =F95-G95 -> 0.0047671236
A96: Example Vendor 070 | B96: Example Contract 095 | D96: Licensing | F96: 156240 | G96: 156240 | H96: =F96-G96 -> 0
A97: Example Vendor 070 | B97: Example Contract 096 | D97: Licensing | F97: 8257.445 | G97: 8257.44 | H97: =F97-G97 -> 0.0049972603
A98: Example Vendor 070 | B98: Example Contract 097 | D98: Licensing | F98: 19259.372 | G98: 19259.37 | H98: =F98-G98 -> 0.001660274
A99: Example Vendor 070 | B99: Example Contract 098 | D99: Licensing | F99: 29236.72 | G99: 29236.72 | H99: =F99-G99 -> -0.00021917808
A100: Example Vendor 070 | B100: Example Contract 099 | D100: Licensing | F100: 43215.109 | G100: 43215.11 | H100: =F100-G100 -> -0.00075205481
...

Sheet Summary JT
B1: V1 Budget | C1: V2 Adjustment | D1: V3 Adjustment | E1: Adjusted Budget | F1: Saving From V1 | H1: Sheet | I1: Vendor | J1: Category | K1: 46204 | L1: 46235 | M1: 46266 | N1: 46296 | O1: 46327 | P1: 46357 | Q1: 46388 | R1: 46419 | S1: 46447 | T1: 46478 | U1: 46508 | V1: 46539 | W1: Q1F27 | X1: Q2F27 | Y1: Q3F27 | Z1: Q4F27 | AA1: FY27 Total
A2: Vendor Spend | H2: Consumption | I2: AWS | J2: Usage Optimisation | K2: 606800 | L2: 0 | M2: 0 | N2: 0 | O2: 0 | P2: 0 | Q2: 0 | R2: 0 | S2: 0 | T2: 0 | U2: 0 | V2: 0 | W2: =SUM(K2:M2) -> 606800 | X2: =SUM(N2:P2) -> 0 | Y2: =SUM(Q2:S2) -> 0 | Z2: =SUM(T2:V2) -> 0 | AA2: =SUM(W2:Z2) -> 606800 | AC2: Notes:
A3: FY27 Addressable | B3: =SUM(#REF!) -> #REF! | C3: =SUM(#REF!) -> #REF! | D3: =SUM(#REF!) -> #REF! | E3: =B3+C3+D3 -> #REF! | F3: =B3-E3 -> #REF! | H3: Consumption | I3: LiveAgent | J3: Product rationalisation | K3: 20620.8 | L3: 0 | M3: 0 | N3: 0 | O3: 0 | P3: 0 | Q3: 0 | R3: 0 | S3: 0 | T3: 0 | U3: 0 | V3: 0 | W3: =SUM(K3:M3) -> 20620.8 | X3: =SUM(N3:P3) -> 0 | Y3: =SUM(Q3:S3) -> 0 | Z3: =SUM(T3:V3) -> 0 | AA3: =W3+X3+Y3+Z3 -> 20620.8 | AC3: For contract renewals, FY27 savings are placed in the month of renewal.
A4: Consumption | B4: =SUM(#REF!) -> #REF! | C4: =SUM(#REF!) -> #REF! | D4: =SUM(#REF!) -> #REF! | E4: =B4+C4+D4 -> #REF! | F4: =B4-E4 -> #REF! | H4: Fusion Related | I4: Oracle Corporation Australia Pty Limited | J4: Product rationalisation | K4: 24798 | L4: 0 | M4: 0 | N4: 0 | O4: 0 | P4: 0 | Q4: 0 | R4: 0 | S4: 0 | T4: 0 | U4: 0 | V4: 0 | W4: =SUM(K4:M4) -> 24798 | X4: =SUM(N4:P4) -> 0 | Y4: =SUM(Q4:S4) -> 0 | Z4: =SUM(T4:V4) -> 0 | AA4: =W4+X4+Y4+Z4 -> 24798 | AC4: For items budgeted for but already exited, FY27 savings placed in July.
A5: Post FY 27 | B5: =SUM(#REF!) -> #REF! | C5: =SUM(#REF!) -> #REF! | D5: =SUM(#REF!) -> #REF! | E5: =B5+C5+D5 -> #REF! | F5: =B5-E5 -> #REF! | H5: FY27 Addressable | I5: Adobe Systems Software Ireland Limited | J5: License Optimisation | K5: 0 | L5: 0 | M5: 0 | N5: 0 | O5: 0 | P5: 0 | Q5: 415000 | R5: 0 | S5: 0 | T5: 0 | U5: 0 | V5: 0 | W5: =SUM(K5:M5) -> 0 | X5: =SUM(N5:P5) -> 0 | Y5: =SUM(Q5:S5) -> 415000 | Z5: =SUM(T5:V5) -> 0 | AA5: =W5+X5+Y5+Z5 -> 415000 | AC5: For items budgeted for but already decided against, FY27 savings placed in July.
A6: New Spend | B6: =SUM(#REF!) -> #REF! | C6: =SUM(#REF!) -> #REF! | D6: =SUM(#REF!) -> #REF! | E6: =B6+C6+D6 -> #REF! | F6: =B6-E6 -> #REF! | H6: FY27 Addressable | I6: AWS Marketplace - Splunk | J6: License Optimisation | K6: 0 | L6: 0 | M6: 0 | N6: 0 | O6: 0 | P6: 0 | Q6: 75000 | R6: 0 | S6: 0 | T6: 0 | U6: 0 | V6: 0 | W6: =SUM(K6:M6) -> 0 | X6: =SUM(N6:P6) -> 0 | Y6: =SUM(Q6:S6) -> 75000 | Z6: =SUM(T6:V6) -> 0 | AA6: =W6+X6+Y6+Z6 -> 75000 | AC6: For items where we bugeted to increase licenses, but have now decided to remain at FY26 levels, FY27 savings placed in July.
A7: Microsoft Related | B7: =SUM(#REF!) -> #REF! | C7: =SUM(#REF!) -> #REF! | D7: =SUM(#REF!) -> #REF! | E7: =B7+C7+D7 -> #REF! | F7: =B7-E7 -> #REF! | H7: FY27 Addressable | I7: China Telecom | J7: Transformation Activities | K7: 31644 | L7: 0 | M7: 0 | N7: 0 | O7: 0 | P7: 0 | Q7: 0 | R7: 0 | S7: 0 | T7: 0 | U7: 0 | V7: 0 | W7: =SUM(K7:M7) -> 31644 | X7: =SUM(N7:P7) -> 0 | Y7: =SUM(Q7:S7) -> 0 | Z7: =SUM(T7:V7) -> 0 | AA7: =W7+X7+Y7+Z7 -> 31644 | AC7: Consumption savings for FY27 placed in July.
A8: Total Vendor Spend: | B8: =SUM(B3:B7) -> #REF! | C8: =SUM(C3:C7) -> #REF! | D8: =SUM(D3:D7) -> #REF! | E8: =SUM(E3:E7) -> #REF! | F8: =SUM(F3:F7) -> #REF! | H8: FY27 Addressable | I8: ContactMonkey | J8: License Optimisation | K8: 0 | L8: 20000 | M8: 0 | N8: 0 | O8: 0 | P8: 0 | Q8: 0 | R8: 0 | S8: 0 | T8: 0 | U8: 0 | V8: 0 | W8: =SUM(K8:M8) -> 20000 | X8: =SUM(N8:P8) -> 0 | Y8: =SUM(Q8:S8) -> 0 | Z8: =SUM(T8:V8) -> 0 | AA8: =W8+X8+Y8+Z8 -> 20000 | AC8: I'm not 100% convinced about LiveAgent as, from the last emails I saw, it was on the list to sunset but not immediately.
H9: FY27 Addressable | I9: Digital Mass | J9: Product rationalisation | K9: 33330.36 | L9: 0 | M9: 0 | N9: 0 | O9: 0 | P9: 0 | Q9: 0 | R9: 0 | S9: 0 | T9: 0 | U9: 0 | V9: 0 | W9: =SUM(K9:M9) -> 33330.36 | X9: =SUM(N9:P9) -> 0 | Y9: =SUM(Q9:S9) -> 0 | Z9: =SUM(T9:V9) -> 0 | AA9: =W9+X9+Y9+Z9 -> 33330.36
A10: Non-Vendor Spend | H10: FY27 Addressable | I10: Dragon Metrics | J10: Product rationalisation | K10: 13440 | L10: 0 | M10: 0 | N10: 0 | O10: 0 | P10: 0 | Q10: 0 | R10: 0 | S10: 0 | T10: 0 | U10: 0 | V10: 0 | W10: =SUM(K10:M10) -> 13440 | X10: =SUM(N10:P10) -> 0 | Y10: =SUM(Q10:S10) -> 0 | Z10: =SUM(T10:V10) -> 0 | AA10: =W10+X10+Y10+Z10 -> 13440
A11: Staff Aug | B11: =SUM(#REF!) -> #REF! | C11: =SUM(#REF!) -> #REF! | D11: =SUM(#REF!) -> #REF! | E11: =B11+C11+D11 -> #REF! | F11: =B11-E11 -> #REF! | H11: FY27 Addressable | I11: Equinix Australia Pty Ltd | J11: Product rationalisation | K11: 0 | L11: 0 | M11: 0 | N11: 0 | O11: 0 | P11: 0 | Q11: 0 | R11: 0 | S11: 0 | T11: 0 | U11: 23871.53 | V11: 0 | W11: =SUM(K11:M11) -> 0 | X11: =SUM(N11:P11) -> 0 | Y11: =SUM(Q11:S11) -> 0 | Z11: =SUM(T11:V11) -> 23871.53 | AA11: =W11+X11+Y11+Z11 -> 23871.53
A12: Professional Consultancy | B12: =SUM(#REF!) -> #REF! | C12: =SUM(#REF!) -> #REF! | D12: =SUM(#REF!) -> #REF! | E12: =B12+C12+D12 -> #REF! | F12: =B12-E12 -> #REF! | H12: FY27 Addressable | I12: Happy Scribe | J12: Product rationalisation | K12: 588 | L12: 0 | M12: 0 | N12: 0 | O12: 0 | P12: 0 | Q12: 0 | R12: 0 | S12: 0 | T12: 0 | U12: 0 | V12: 0 | W12: =SUM(K12:M12) -> 588 | X12: =SUM(N12:P12) -> 0 | Y12: =SUM(Q12:S12) -> 0 | Z12: =SUM(T12:V12) -> 0 | AA12: =W12+X12+Y12+Z12 -> 588
A13: Miscellaneous | B13: =SUM(#REF!) -> #REF! | C13: =SUM(#REF!) -> #REF! | D13: =SUM(#REF!) -> #REF! | E13: =B13+C13+D13 -> #REF! | F13: =B13-E13 -> #REF! | H13: FY27 Addressable | I13: Import.io | J13: License Optimisation | K13: 30000 | L13: 0 | M13: 0 | N13: 0 | O13: 0 | P13: 0 | Q13: 0 | R13: 0 | S13: 0 | T13: 0 | U13: 0 | V13: 0 | W13: =SUM(K13:M13) -> 30000 | X13: =SUM(N13:P13) -> 0 | Y13: =SUM(Q13:S13) -> 0 | Z13: =SUM(T13:V13) -> 0 | AA13: =W13+X13+Y13+Z13 -> 30000
A14: Non-Tech Budget | B14: =SUM(#REF!) -> #REF! | C14: =SUM(#REF!) -> #REF! | D14: =SUM(#REF!) -> #REF! | E14: =B14+C14+D14 -> #REF! | F14: =B14-E14 -> #REF! | H14: FY27 Addressable | I14: Ionic Inc. | J14: License Optimisation | K14: 0 | L14: 0 | M14: 0 | N14: 0 | O14: 0 | P14: 0 | Q14: 11000 | R14: 0 | S14: 0 | T14: 0 | U14: 0 | V14: 0 | W14: =SUM(K14:M14) -> 0 | X14: =SUM(N14:P14) -> 0 | Y14: =SUM(Q14:S14) -> 11000 | Z14: =SUM(T14:V14) -> 0 | AA14: =W14+X14+Y14+Z14 -> 11000
A15: Total Non-Vendor Spend: | B15: =SUM(B11:B14) -> #REF! | C15: =SUM(C11:C14) -> #REF! | D15: =SUM(D11:D14) -> #REF! | E15: =SUM(E11:E14) -> #REF! | F15: =SUM(F11:F14) -> #REF! | H15: FY27 Addressable | I15: LinkedIn Singapore Pte Ltd | J15: License Optimisation | K15: 0 | L15: 195657 | M15: 0 | N15: 0 | O15: 0 | P15: 0 | Q15: 0 | R15: 0 | S15: 0 | T15: 0 | U15: 0 | V15: 0 | W15: =SUM(K15:M15) -> 195657 | X15: =SUM(N15:P15) -> 0 | Y15: =SUM(Q15:S15) -> 0 | Z15: =SUM(T15:V15) -> 0 | AA15: =W15+X15+Y15+Z15 -> 195657
H16: FY27 Addressable | I16: Lucid Software Inc. | J16: License Optimisation | K16: 30000 | L16: 0 | M16: 0 | N16: 0 | O16: 0 | P16: 0 | Q16: 0 | R16: 0 | S16: 0 | T16: 0 | U16: 0 | V16: 0 | W16: =SUM(K16:M16) -> 30000 | X16: =SUM(N16:P16) -> 0 | Y16: =SUM(Q16:S16) -> 0 | Z16: =SUM(T16:V16) -> 0 | AA16: =W16+X16+Y16+Z16 -> 30000
H17: FY27 Addressable | I17: UXCam Inc. | J17: License Optimisation | K17: 13000 | L17: 0 | M17: 0 | N17: 0 | O17: 0 | P17: 0 | Q17: 0 | R17: 0 | S17: 0 | T17: 0 | U17: 0 | V17: 0 | W17: =SUM(K17:M17) -> 13000 | X17: =SUM(N17:P17) -> 0 | Y17: =SUM(Q17:S17) -> 0 | Z17: =SUM(T17:V17) -> 0 | AA17: =W17+X17+Y17+Z17 -> 13000
A18: Fusion Related | B18: =SUM(#REF!) -> #REF! | C18: =SUM(#REF!) -> #REF! | D18: =SUM(#REF!) -> #REF! | E18: =B18+C18+D18 -> #REF! | F18: =B18-E18 -> #REF! | H18: FY27 Addressable | I18: Voucherify P.S.A | J18: License Optimisation | K18: 0 | L18: 0 | M18: 0 | N18: 0 | O18: 0 | P18: 7000 | Q18: 0 | R18: 0 | S18: 0 | T18: 0 | U18: 0 | V18: 0 | W18: =SUM(K18:M18) -> 0 | X18: =SUM(N18:P18) -> 7000 | Y18: =SUM(Q18:S18) -> 0 | Z18: =SUM(T18:V18) -> 0 | AA18: =W18+X18+Y18+Z18 -> 7000
H19: FY27 Addressable | I19: Walkme | J19: Product rationalisation | K19: 187066 | L19: 0 | M19: 0 | N19: 0 | O19: 0 | P19: 0 | Q19: 0 | R19: 0 | S19: 0 | T19: 0 | U19: 0 | V19: 0 | W19: =SUM(K19:M19) -> 187066 | X19: =SUM(N19:P19) -> 0 | Y19: =SUM(Q19:S19) -> 0 | Z19: =SUM(T19:V19) -> 0 | AA19: =W19+X19+Y19+Z19 -> 187066
A20: Total Vendor Spend: | B20: =B18+B15+B8 -> #REF! | C20: =C18+C15+C8 -> #REF! | D20: =D18+D15+D8 -> #REF! | E20: =E18+E15+E8 -> #REF! | F20: =F18+F15+F8 -> #REF! | H20: FY27 Addressable | I20: Zoom Video Communications Inc | J20: License Optimisation | K20: 0 | L20: 0 | M20: 0 | N20: 0 | O20: 0 | P20: 0 | Q20: 0 | R20: 0 | S20: 0 | T20: 0 | U20: 0 | V20: 23000 | W20: =SUM(K20:M20) -> 0 | X20: =SUM(N20:P20) -> 0 | Y20: =SUM(Q20:S20) -> 0 | Z20: =SUM(T20:V20) -> 23000 | AA20: =W20+X20+Y20+Z20 -> 23000
H21: Microsoft Related | I21: Microsoft | J21: License Optimisation | K21: 0 | L21: 0 | M21: 0 | N21: 1999808.8 | O21: 0 | P21: 0 | Q21: 0 | R21: 0 | S21: 0 | T21: 0 | U21: 0 | V21: 0 | W21: =SUM(K21:M21) -> 0 | X21: =SUM(N21:P21) -> 1999808.8 | Y21: =SUM(Q21:S21) -> 0 | Z21: =SUM(T21:V21) -> 0 | AA21: =W21+X21+Y21+Z21 -> 1999808.8
A22: Jessy File: | B22: 42325358 | H22: New Spend | I22: Microsoft Pty Ltd | J22: Product rationalisation | K22: 243750 | L22: 0 | M22: 0 | N22: 0 | O22: 0 | P22: 0 | Q22: 0 | R22: 0 | S22: 0 | T22: 0 | U22: 0 | V22: 0 | W22: =SUM(K22:M22) -> 243750 | X22: =SUM(N22:P22) -> 0 | Y22: =SUM(Q22:S22) -> 0 | Z22: =SUM(T22:V22) -> 0 | AA22: =W22+X22+Y22+Z22 -> 243750
H23: Post FY 27 | I23: AWS Marketplace - GitLab | J23: Capitalisation | K23: 182510 | L23: 0 | M23: 0 | N23: 0 | O23: 0 | P23: 0 | Q23: 0 | R23: 0 | S23: 0 | T23: 0 | U23: 0 | V23: 0 | W23: =SUM(K23:M23) -> 182510 | X23: =SUM(N23:P23) -> 0 | Y23: =SUM(Q23:S23) -> 0 | Z23: =SUM(T23:V23) -> 0 | AA23: =W23+X23+Y23+Z23 -> 182510
A24: Difference: | B24: =B20-B22 -> #REF! | C24: Budget transfer of Dilligent for V1 | H24: Post FY 27 | I24: Snyk Limited | J24: License Optimisation | K24: 93836.8 | L24: 0 | M24: 0 | N24: 0 | O24: 0 | P24: 0 | Q24: 0 | R24: 0 | S24: 0 | T24: 0 | U24: 0 | V24: 0 | W24: =SUM(K24:M24) -> 93836.8 | X24: =SUM(N24:P24) -> 0 | Y24: =SUM(Q24:S24) -> 0 | Z24: =SUM(T24:V24) -> 0 | AA24: =W24+X24+Y24+Z24 -> 93836.8
H25: Professional Consultancy | I25: Mantel Group Pty Ltd | J25: Usage Optimisation | K25: 30000 | L25: 0 | M25: 0 | N25: 0 | O25: 0 | P25: 0 | Q25: 0 | R25: 0 | S25: 0 | T25: 0 | U25: 0 | V25: 0 | W25: =SUM(K25:M25) -> 30000 | X25: =SUM(N25:P25) -> 0 | Y25: =SUM(Q25:S25) -> 0 | Z25: =SUM(T25:V25) -> 0 | AA25: =W25+X25+Y25+Z25 -> 30000
H26: Staff Aug | I26: ConnectOS Pty Ltd | J26: Usage Optimisation | K26: 570000 | L26: 0 | M26: 0 | N26: 0 | O26: 0 | P26: 0 | Q26: 0 | R26: 0 | S26: 0 | T26: 0 | U26: 0 | V26: 0 | W26: =SUM(K26:M26) -> 570000 | X26: =SUM(N26:P26) -> 0 | Y26: =SUM(Q26:S26) -> 0 | Z26: =SUM(T26:V26) -> 0 | AA26: =W26+X26+Y26+Z26 -> 570000
I27: Total Cost Out: | K27: =SUM(K2:K26) -> 2111384 | L27: =SUM(L2:L26) -> 215657 | M27: =SUM(M2:M26) -> 0 | N27: =SUM(N2:N26) -> 1999808.8 | O27: =SUM(O2:O26) -> 0 | P27: =SUM(P2:P26) -> 7000 | Q27: =SUM(Q2:Q26) -> 501000 | R27: =SUM(R2:R26) -> 0 | ... AA27: =SUM(AA2:AA26) -> 4881721.3
I29: Vendor | J29: Category
A30: - | H30: Fusion Related | I30: Rimini Street, Inc | K30: -122582.57 | L30: 0 | M30: 0 | N30: 0 | O30: 0 | P30: 0 | Q30: 0 | R30: 0 | S30: 0 | T30: 0 | U30: 0 | V30: 0 | W30: =SUM(K30:M30) -> -122582.57 | X30: =SUM(N30:P30) -> 0 | Y30: =SUM(Q30:S30) -> 0 | Z30: =SUM(T30:V30) -> 0 | AA30: =W30+X30+Y30+Z30 -> -122582.57
H31: Post FY 27 | I31: Diligent One Platform | K31: -20000 | L31: 0 | M31: 0 | N31: 0 | O31: 0 | P31: 0 | Q31: 0 | R31: 0 | S31: 0 | T31: 0 | U31: 0 | V31: 0 | W31: =SUM(K31:M31) -> -20000 | X31: =SUM(N31:P31) -> 0 | Y31: =SUM(Q31:S31) -> 0 | Z31: =SUM(T31:V31) -> 0 | AA31: =W31+X31+Y31+Z31 -> -20000
H32: Post FY 27 | I32: Gartner Midsize Enterprise | K32: -171000 | L32: 0 | M32: 0 | N32: 0 | O32: 0 | P32: 0 | Q32: 0 | R32: 0 | S32: 0 | T32: 0 | U32: 0 | V32: 0 | W32: =SUM(K32:M32) -> -171000 | X32: =SUM(N32:P32) -> 0 | Y32: =SUM(Q32:S32) -> 0 | Z32: =SUM(T32:V32) -> 0 | AA32: =W32+X32+Y32+Z32 -> -171000
H33: FY27 Addressable | I33: Ahrefs Pte Ltd | K33: -33440 | L33: 0 | M33: 0 | N33: 0 | O33: 0 | P33: 0 | Q33: 0 | R33: 0 | S33: 0 | T33: 0 | U33: 0 | V33: 0 | W33: =SUM(K33:M33) -> -33440 | X33: =SUM(N33:P33) -> 0 | Y33: =SUM(Q33:S33) -> 0 | Z33: =SUM(T33:V33) -> 0 | AA33: =W33+X33+Y33+Z33 -> -33440
I34: Total Cost In: | K34: =SUM(K30:K33) -> -347022.57 | L34: =SUM(L30:L33) -> 0 | M34: =SUM(M30:M33) -> 0 | N34: =SUM(N30:N33) -> 0 | O34: =SUM(O30:O33) -> 0 | P34: =SUM(P30:P33) -> 0 | Q34: =SUM(Q30:Q33) -> 0 | R34: =SUM(R30:R33) -> 0 | ... AA34: =SUM(AA30:AA33) -> -347022.57

Sheet FY27 Budget Template
B1: ***DO NOT SORT THIS PAGE. IT STUFFS THE FORMULAS*** | D1: ALL YELLOW CELLS REQUIRE INPUT | H1: 319 - pure OSM direct cost | J1: =39258-39258 -> 0 | L1: =SUBTOTAL(9,L4:L1001) -> 42325358 | N1: =SUBTOTAL(9,N4:N1001) -> -2741765.8 | O1: =SUBTOTAL(9,O4:O1001) -> -822508 | P1: =SUBTOTAL(9,P4:P1001) -> 38761084
L2: BUDGET | P2: BUDGET
A3: Ref | B3: Vendor | C3: Product | D3: Function | E3: GTLT/Tech Owner/ Business Owner | F3: CC | G3: GL | H3: Type | I3: Start | J3: End | K3: Term (months) | L3: F27B Total | M3: Var F27 v F26 (Fav)/Unfav (v1) | N3: Adjustment V2 | O3: Adjustment V3 | P3: F27B Total V3
A4: 263 | B4: Abebe Tedila Mengistie | D4: Tech | F4: 511HDO | G4: 8700 | H4: Consumption | K4: =IF(OR(I4="",J4=""),"Monthly",IF(J4<I4,0,(YEAR(J4)-YEAR(I4))*12+(MONTH(J4)-MONTH(I4))+1-IF(DAY(J4)<DAY(I4),1,0))) -> Monthly | L4: 20731.599 | M4: 20731.599 | P4: 20731.599
A5: 30 | B5: Adjust GmbH | C5: Adjust Core - 1,000,000 Conversions | D5: Marketing | E5: Neeraja/Amudha | F5: 213BTI | G5: 8200 | H5: Fixed | I5: 45901 | J5: 46265 | K5: =IF(OR(I5="",J5=""),"",IF(J5<I5,0,(YEAR(J5)-YEAR(I5))*12+(MONTH(J5)-MONTH(I5))+1-IF(DAY(J5)<DAY(I5),1,0))) -> 12 | L5: 21602.37 | M5: 5949.4456 | P5: 21602.37
A6: 31 | B6: Adobe Systems Software Ireland Limited | C6: Marketo - Student Placement (Year 1- 1.2M, Year 2- $1.5M, Year 3- $1.7M) | D6: Marketing | E6: Neeraja/ Antony Nelson/Michelle Callanan | F6: 213BTI | G6: 8200 | H6: Fixed | I6: 45292 | J6: 46387 | K6: =IF(OR(I6="",J6=""),"",IF(J6<I6,0,(YEAR(J6)-YEAR(I6))*12+(MONTH(J6)-MONTH(I6))+1-IF(DAY(J6)<DAY(I6),1,0))) -> 36 | L6: 1806000 | M6: 347802.13 | N6: -275000 | P6: 1531000
A7: 32 | B7: Adobe Systems Software Ireland Limited | C7: Marketo Engage - Additional Dynamic Chat seats - 70 | D7: Marketing | E7: Neeraja/ Antony Nelson/Michelle Callanan | F7: 213BTI | G7: 8200 | H7: Fixed | I7: 45505 | J7: 46392 | K7: =IF(OR(I7="",J7=""),"",IF(J7<I7,0,(YEAR(J7)-YEAR(I7))*12+(MONTH(J7)-MONTH(I7))+1-IF(DAY(J7)<DAY(I7),1,0))) -> 30 | L7: 76651.437 | M7: 18278.201 | N7: -10000 | P7: 66651.437
A8: FY27B | B8: Ahrefs, SEMRush | C8: SEO Tools - Regional | D8: Marketing | E8: Michelle C/Joel Knight | F8: 511HDO | G8: 8200 | K8: =IF(OR(I8="",J8=""),"Monthly",IF(J8<I8,0,(YEAR(J8)-YEAR(I8))*12+(MONTH(J8)-MONTH(I8))+1-IF(DAY(J8)<DAY(I8),1,0))) -> Monthly | L8: 20000 | M8: 20000 | O8: 33440 | P8: 53440
A9: 1 | B9: Amazon Web Services Australia Pty Ltd | C9: PPA Commitment | D9: DM | E9: Neeraja / Jayakumar | F9: 794HGB01 | G9: 8200 | H9: Consumption | I9: 45870 | J9: 46965 | K9: =IF(OR(I9="",J9=""),"",IF(J9<I9,0,(YEAR(J9)-YEAR(I9))*12+(MONTH(J9)-MONTH(I9))+1-IF(DAY(J9)<DAY(I9),1,0))) -> 36 | L9: -672153 | M9: -672153 | P9: -672153
A10: 1 | B10: Amazon Web Services Australia Pty Ltd | C10: PPA Commitment | D10: Envoy | E10: Neeraja / Jayakumar | F10: 346 Envoy | G10: 8200 | H10: Consumption | I10: 45870 | J10: 46965 | K10: =IF(OR(I10="",J10=""),"",IF(J10<I10,0,(YEAR(J10)-YEAR(I10))*12+(MONTH(J10)-MONTH(I10))+1-IF(DAY(J10)<DAY(I10),1,0))) -> 36 | L10: -11351 | M10: -11351 | P10: -11351
A11: 1 | B11: Amazon Web Services Australia Pty Ltd | C11: PPA Commitment | D11: Envoy | E11: Neeraja / Jayakumar | F11: 346 Envoy | G11: 8200 | H11: Consumption | I11: 45870 | J11: 46965 | K11: =IF(OR(I11="",J11=""),"",IF(J11<I11,0,(YEAR(J11)-YEAR(I11))*12+(MONTH(J11)-MONTH(I11))+1-IF(DAY(J11)<DAY(I11),1,0))) -> 36 | L11: 11351 | M11: 11351 | P11: 11351
B12: Amazon Web Services Australia Pty Ltd | C12: PPA Commitment | D12: Tech | E12: Neeraja / Jayakumar | F12: 511HDO | G12: 8200 | H12: Consumption | I12: 45870 | J12: 46965 | K12: =IF(OR(I12="",J12=""),"",IF(J12<I12,0,(YEAR(J12)-YEAR(I12))*12+(MONTH(J12)-MONTH(I12))+1-IF(DAY(J12)<DAY(I12),1,0))) -> 36 | L12: 46800 | M12: 46800 | N12: -46800 | P12: 0
A13: 1 | B13: Amazon Web Services Australia Pty Ltd | C13: PPA Commitment | D13: LT | E13: Neeraja / Jayakumar | F13: 319IEO | G13: 8200 | H13: Consumption | I13: 45870 | J13: 46965 | K13: =IF(OR(I13="",J13=""),"",IF(J13<I13,0,(YEAR(J13)-YEAR(I13))*12+(MONTH(J13)-MONTH(I13))+1-IF(DAY(J13)<DAY(I13),1,0))) -> 36 | L13: 273914 | M13: 64420.05 | N13: -30000 | P13: 243914
A14: 1 | B14: Amazon Web Services Australia Pty Ltd | C14: PPA Commitment | D14: Analytics | E14: Neeraja / Jayakumar | F14: 513HDO | G14: 8200 | H14: Consumption | I14: 45870 | J14: 46965 | K14: =IF(OR(I14="",J14=""),"",IF(J14<I14,0,(YEAR(J14)-YEAR(I14))*12+(MONTH(J14)-MONTH(I14))+1-IF(DAY(J14)<DAY(I14),1,0))) -> 36 | L14: 354709 | M14: -18401.51 | N14: -40000 | P14: 314709
A15: 1 | B15: Amazon Web Services Australia Pty Ltd | C15: PPA Commitment | D15: DM | E15: Neeraja / Jayakumar | F15: 794HGB01 | G15: 8200 | H15: Consumption | I15: 45870 | J15: 46965 | K15: =IF(OR(I15="",J15=""),"",IF(J15<I15,0,(YEAR(J15)-YEAR(I15))*12+(MONTH(J15)-MONTH(I15))+1-IF(DAY(J15)<DAY(I15),1,0))) -> 36 | L15: 672153 | M15: 672153 | P15: 672153
A16: 1 | B16: Amazon Web Services Australia Pty Ltd | C16: PPA Commitment | D16: SP | E16: Neeraja / Jayakumar | F16: 213BTI | G16: 8200 | H16: Consumption | I16: 45870 | J16: 46965 | K16: =IF(OR(I16="",J16=""),"",IF(J16<I16,0,(YEAR(J16)-YEAR(I16))*12+(MONTH(J16)-MONTH(I16))+1-IF(DAY(J16)<DAY(I16),1,0))) -> 36 | L16: 1606542 | M16: 221589.11 | N16: -190000 | P16: 1416542
A17: 1 | B17: Amazon Web Services Australia Pty Ltd | C17: PPA Commitment | D17: LT | E17: Neeraja / Jayakumar | F17: 308IEA | G17: 8200 | H17: Consumption | I17: 45870 | J17: 46965 | K17: =IF(OR(I17="",J17=""),"",IF(J17<I17,0,(YEAR(J17)-YEAR(I17))*12+(MONTH(J17)-MONTH(I17))+1-IF(DAY(J17)<DAY(I17),1,0))) -> 36 | L17: 2721867 | M17: 177350.91 | N17: -300000 | P17: 2421867
A18: 34 | B18: APNIC Pty Ltd | C18: Annual Membership, IDP Public IP in Aus | D18: Cyber | E18: Simon Cowley | F18: 514HDO | G18: 8200 | H18: Fixed | I18: 45931 | J18: 46295 | K18: =IF(OR(I18="",J18=""),"",IF(J18<I18,0,(YEAR(J18)-YEAR(I18))*12+(MONTH(J18)-MONTH(I18))+1-IF(DAY(J18)<DAY(I18),1,0))) -> 12 | L18: 2115.839 | M18: -438.80164 | P18: 2115.839
A19: 35 | B19: App Samurai Limited | C19: Storyly | D19: DM | E19: Neeraja / Sasi kumar | F19: 516HDO | G19: 8200 | H19: Fixed | I19: 45870 | J19: 46234 | K19: =IF(OR(I19="",J19=""),"",IF(J19<I19,0,(YEAR(J19)-YEAR(I19))*12+(MONTH(J19)-MONTH(I19))+1-IF(DAY(J19)<DAY(I19),1,0))) -> 12 | L19: 16835.047 | M19: 7813.3442 | P19: 16835.047
A20: 36 | B20: Apple Inc. | C20: DC Apple Developer Account - IDP Connect (Lower enviroment) | D20: DM,LT & SP | E20: Neeraja / Kishore Mohanarangam | F20: 516HDO | G20: 8200 | H20: Fixed | I20: 46046 | J20: 46410 | K20: =IF(OR(I20="",J20=""),"",IF(J20<I20,0,(YEAR(J20)-YEAR(I20))*12+(MONTH(J20)-MONTH(I20))+1-IF(DAY(J20)<DAY(I20),1,0))) -> 12 | L20: 839.9782 | M20: 628.97504 | P20: 839.9782
A21: 2 | B21: Appointlet | D21: SP | E21: Neeraja/Bala | F21: 516HDO | G21: 8200 | H21: Consumption | I21: 46000 | J21: 46364 | K21: =IF(OR(I21="",J21=""),"",IF(J21<I21,0,(YEAR(J21)-YEAR(I21))*12+(MONTH(J21)-MONTH(I21))+1-IF(DAY(J21)<DAY(I21),1,0))) -> 12 | L21: 16000 | M21: 10800 | P21: 16000
A22: 39 | B22: Aussie Broadband Limited | C22: Aussie Broadband - Fibre Links | E22: Lewis Lee | F22: 517HDO | G22: 8800 | H22: Fixed | I22: 45839 | J22: 46934 | K22: =IF(OR(I22="",J22=""),"",IF(J22<I22,0,(YEAR(J22)-YEAR(I22))*12+(MONTH(J22)-MONTH(I22))+1-IF(DAY(J22)<DAY(I22),1,0))) -> 36 | L22: 48151.609 | M22: 4938.9725 | P22: 48151.609
A23: 40 | B23: AwardForce | C23: Awards Management Platform - to Manage Award Programs | D23: Marketing | E23: Michelle Callanan/ Annie Sun | F23: 511HDO | G23: 8200 | H23: Fixed | I23: 45990 | J23: 46354 | K23: =IF(OR(I23="",J23=""),"",IF(J23<I23,0,(YEAR(J23)-YEAR(I23))*12+(MONTH(J23)-MONTH(I23))+1-IF(DAY(J23)<DAY(I23),1,0))) -> 12 | L23: 15442.021 | M23: 2244.8592 | P23: 15442.021
A24: FY27B | B24: AWS Marketplace - Anthropic PBC | C24: Claude | D24: SP | E24: Business Case: C213 AAV | F24: 213BTI | G24: 8200 | H24: Consumption | K24: =IF(OR(I24="",J24=""),"Monthly",IF(J24<I24,0,(YEAR(J24)-YEAR(I24))*12+(MONTH(J24)-MONTH(I24))+1-IF(DAY(J24)<DAY(I24),1,0))) -> Monthly | L24: 102217 | M24: 102217 | P24: 102217
A25: FY27B | B25: AWS Marketplace - Anthropic PBC | C25: Claude | D25: SP | E25: Stuart Nickols Business Case: C205 Navi | F25: 213BTI | G25: 8200 | H25: Consumption | K25: =IF(OR(I25="",J25=""),"Monthly",IF(J25<I25,0,(YEAR(J25)-YEAR(I25))*12+(MONTH(J25)-MONTH(I25))+1-IF(DAY(J25)<DAY(I25),1,0))) -> Monthly | L25: 200000 | M25: 200000 | P25: 200000
A26: 4 | B26: AWS Marketplace - ClamAV | C26: BucketAV Software | D26: Cyber | E26: Simon Cowley | F26: 514HDO | G26: 8200 | H26: Consumption | K26: =IF(OR(I26="",J26=""),"",IF(J26<I26,0,(YEAR(J26)-YEAR(I26))*12+(MONTH(J26)-MONTH(I26))+1-IF(DAY(J26)<DAY(I26),1,0))) | L26: 3630 | M26: 497.15 | P26: 3630
A27: 204 | B27: AWS Marketplace - Cloudec | C27: Managed Services | D27: Cloudops | E27: Lewis Lee | F27: 513HDO | G27: 8700 | H27: Fixed | I27: 46056 | J27: 46144 | K27: =IF(OR(I27="",J27=""),"",IF(J27<I27,0,(YEAR(J27)-YEAR(I27))*12+(MONTH(J27)-MONTH(I27))+1-IF(DAY(J27)<DAY(I27),1,0))) -> 3 | L27: 63000 | M27: 12762.447 | P27: 63000
A28: 208 | B28: AWS Marketplace – Commvault | C28: Commvault Cloud SaaS Jumpstart | D28: Platform & Infrastructure | F28: 513HDO | G28: 8200 | H28: Fixed | I28: 46027 | J28: 47122 | K28: =IF(OR(I28="",J28=""),"",IF(J28<I28,0,(YEAR(J28)-YEAR(I28))*12+(MONTH(J28)-MONTH(I28))+1-IF(DAY(J28)<DAY(I28),1,0))) -> 36 | L28: 286994.42 | M28: 167311.09 | P28: 286994.42
A29: 435 | B29: AWS Marketplace – Commvault | D29: Tech | E29: Neeraja/Jayakumar | F29: 490HDO | G29: 8200 | H29: Other | K29: =IF(OR(I29="",J29=""),"Monthly",IF(J29<I29,0,(YEAR(J29)-YEAR(I29))*12+(MONTH(J29)-MONTH(I29))+1-IF(DAY(J29)<DAY(I29),1,0))) -> Monthly | L29: 268316 | M29: 218372.16 | P29: 268316
A30: FY27B | B30: AWS Marketplace - CyberCX | C30: China licenses Premium (220 @USD50) | D30: Cyber | E30: Simon Cowley | F30: 514HDO | G30: 8200 | H30: Fixed | K30: =IF(OR(I30="",J30=""),"Monthly",IF(J30<I30,0,(YEAR(J30)-YEAR(I30))*12+(MONTH(J30)-MONTH(I30))+1-IF(DAY(J30)<DAY(I30),1,0))) -> Monthly | L30: 17600 | M30: 17600 | P30: 17600
A31: 42 | B31: AWS Marketplace - CyberCX | C31: Netskope Enterprise Browser + Support (1500 licenses) | D31: Cyber | E31: Simon Cowley | F31: 514HDO | G31: 8200 | H31: Fixed | K31: =IF(OR(I31="",J31=""),"Monthly",IF(J31<I31,0,(YEAR(J31)-YEAR(I31))*12+(MONTH(J31)-MONTH(I31))+1-IF(DAY(J31)<DAY(I31),1,0))) -> Monthly | L31: 33416.688 | M31: 33416.688 | P31: 33416.688
A32: FY27B | B32: AWS Marketplace - CyberCX | C32: Netskope Enterprise Browser + Support (2500 @ USD16 per license) | D32: Cyber | E32: Simon Cowley | F32: 514HDO | G32: 8200 | H32: Fixed | K32: =IF(OR(I32="",J32=""),"Monthly",IF(J32<I32,0,(YEAR(J32)-YEAR(I32))*12+(MONTH(J32)-MONTH(I32))+1-IF(DAY(J32)<DAY(I32),1,0))) -> Monthly | L32: 64000 | M32: 64000 | P32: 64000
A33: 41 | B33: AWS Marketplace - CyberCX | C33: Netskope SASE Licences + Support (6500 licenses) | D33: Cyber | E33: Simon Cowley | F33: 514HDO | G33: 8200 | H33: Fixed | K33: =IF(OR(I33="",J33=""),"Monthly",IF(J33<I33,0,(YEAR(J33)-YEAR(I33))*12+(MONTH(J33)-MONTH(I33))+1-IF(DAY(J33)<DAY(I33),1,0))) -> Monthly | L33: 919193.6 | M33: 919193.6 | P33: 919193.6
A34: 43 | B34: AWS Marketplace – Docker Inc | C34: SW subscription Docker Business Plan | D34: Tech | E34: Neeraja/Santhosh | F34: 516HDO | G34: 8200 | H34: Fixed | I34: 45775 | J34: 46139 | K34: =IF(OR(I34="",J34=""),"",IF(J34<I34,0,(YEAR(J34)-YEAR(I34))*12+(MONTH(J34)-MONTH(I34))+1-IF(DAY(J34)<DAY(I34),1,0))) -> 12 | L34: 23040 | M34: 302.92932 | P34: 23040
A35: 45 | B35: AWS Marketplace – IBM Software | C35: Cloudability | D35: Tech | E35: Lewis Lee | F35: 513HDO | G35: 8200 | H35: Fixed | I35: 45839 | J35: 46203 | K35: =IF(OR(I35="",J35=""),"",IF(J35<I35,0,(YEAR(J35)-YEAR(I35))*12+(MONTH(J35)-MONTH(I35))+1-IF(DAY(J35)<DAY(I35),1,0))) -> 12 | L35: 75000 | M35: 15563.63 | P35: 75000
A36: 46 | B36: AWS Marketplace - Marketo | C36: Marketo Engage | D36: Marketing | E36: Neeraja/Michelle Callanan | F36: 308IEA | G36: 8200 | H36: Fixed | I36: 46084 | J36: 46392 | K36: =IF(OR(I36="",J36=""),"",IF(J36<I36,0,(YEAR(J36)-YEAR(I36))*12+(MONTH(J36)-MONTH(I36))+1-IF(DAY(J36)<DAY(I36),1,0))) -> 11 | L36: 836817.43 | M36: 59654.381 | N36: -130000 | P36: 706817.43
A37: 47 | B37: AWS Marketplace - N2WS | C37: Aws Backups | D37: Platform & Infrastructure | E37: Neeraja | F37: 513HDO | G37: 8200 | H37: Fixed | I37: 45839 | J37: 46203 | K37: =IF(OR(I37="",J37=""),"",IF(J37<I37,0,(YEAR(J37)-YEAR(I37))*12+(MONTH(J37)-MONTH(I37))+1-IF(DAY(J37)<DAY(I37),1,0))) -> 12 | L37: 9600 | M37: 1578.8438 | P37: 9600
A38: 5 | B38: AWS Marketplace – NGINX Software | C38: Load balancer | D38: DM | E38: Neeraja/Gayathri | F38: 213BTI | G38: 8200 | H38: Consumption | I38: 45839 | J38: 46203 | K38: =IF(OR(I38="",J38=""),"",IF(J38<I38,0,(YEAR(J38)-YEAR(I38))*12+(MONTH(J38)-MONTH(I38))+1-IF(DAY(J38)<DAY(I38),1,0))) -> 12 | L38: 15000 | M38: -37486.178 | P38: 15000
A39: 53 | B39: AWS Marketplace - Splunk | C39: Splunk Cloud Subscription | D39: Cyber | E39: Simon Cowley | F39: 514HDO | G39: 8200 | H39: Fixed | I39: 46014 | J39: 46378 | K39: =IF(OR(I39="",J39=""),"",IF(J39<I39,0,(YEAR(J39)-YEAR(I39))*12+(MONTH(J39)-MONTH(I39))+1-IF(DAY(J39)<DAY(I39),1,0))) -> 12 | L39: 819389.08 | M39: 269261.89 | P39: 819389.08
A40: 54 | B40: AWS Marketplace - Splunk | C40: Splunk Observability | D40: Cyber | E40: Simon Cowley | F40: 514HDO | G40: 8200 | H40: Fixed | I40: 45892 | J40: 46378 | K40: =IF(OR(I40="",J40=""),"",IF(J40<I40,0,(YEAR(J40)-YEAR(I40))*12+(MONTH(J40)-MONTH(I40))+1-IF(DAY(J40)<DAY(I40),1,0))) -> 16 | L40: 144542.94 | M40: -132147.4 | P40: 144542.94
A41: 9 | B41: AWS Marketplace – Workato Inc | C41: 1M Tasks x 7 (inc Support) - based on OSM consumption | D41: LT | E41: Neeraja/Jayakumar | F41: 319IEO | G41: 8200 | H41: Consumption | I41: 45931 | J41: 47026 | K41: =IF(OR(I41="",J41=""),"",IF(J41<I41,0,(YEAR(J41)-YEAR(I41))*12+(MONTH(J41)-MONTH(I41))+1-IF(DAY(J41)<DAY(I41),1,0))) -> 36 | L41: 105180.07 | M41: -13715.511 | P41: 105180.07
A42: 8 | B42: AWS Marketplace – Workato Inc | C42: Enterprise Edition (inc Support) | D42: Tech | E42: Neeraja/Jayakumar | F42: 516HDO | G42: 8200 | H42: Fixed | I42: 45931 | J42: 47026 | K42: =IF(OR(I42="",J42=""),"",IF(J42<I42,0,(YEAR(J42)-YEAR(I42))*12+(MONTH(J42)-MONTH(I42))+1-IF(DAY(J42)<DAY(I42),1,0))) -> 36 | L42: 161352.65 | M42: 63194.527 | P42: 161352.65
A43: 9 | B43: AWS Marketplace – Workato Inc | C43: Workato is an iPaaS solution tool to automate workflows and integrate applications | D43: SP | E43: Neeraja/Jayakumar | F43: 213BTI | G43: 8200 | H43: Consumption | K43: Monthly | L43: 10000 | M43: 10000 | P43: 10000
A44: MISC | B44: Balancing line to agree back to CORTH after volume adjustment by FSS | F44: 319IEO | G44: 8200 | H44: Consumption | L44: -273733.87 | M44: -176270.97 | P44: -273733.87
A45: 56 | B45: BDO Services Pty Ltd | C45: BDO Lead SaaS Annual Licence Fee (Lease Accounting) | D45: Finance | E45: Neeraja | F45: 516HDO | G45: 8200 | H45: Fixed | I45: 45748 | J45: 46112 | K45: =IF(OR(I45="",J45=""),"",IF(J45<I45,0,(YEAR(J45)-YEAR(I45))*12+(MONTH(J45)-MONTH(I45))+1-IF(DAY(J45)<DAY(I45),1,0))) -> 12 | L45: 30750 | M45: 626.30326 | P45: 30750
A46: 209 | B46: Beijing Sinnet Technology Co., Ltd. | C46: Amazon in China, Project Panda, to change to 308 in FY27 | D46: LT | E46: Jason Thunder | F46: 308IEA | G46: 8200 | H46: Consumption | K46: =IF(OR(I46="",J46=""),"Monthly",IF(J46<I46,0,(YEAR(J46)-YEAR(I46))*12+(MONTH(J46)-MONTH(I46))+1-IF(DAY(J46)<DAY(I46),1,0))) -> Monthly | L46: 31886.843 | M46: 31886.843 | P46: 31886.843
A47: 210 | B47: BitTitan | D47: Shared | E47: Lewis Lee | F47: 517HDO | G47: 8200 | K47: =IF(OR(I47="",J47=""),"",IF(J47<I47,0,(YEAR(J47)-YEAR(I47))*12+(MONTH(J47)-MONTH(I47))+1-IF(DAY(J47)<DAY(I47),1,0))) | L47: 497.387 | M47: 45.217 | P47: 497.387
A48: 58 | B48: Blackline Systems | C48: OnDemand Basic Black + Premium 85 Users | D48: Finance | E48: Neeraja | F48: 516HDO | G48: 8200 | H48: Fixed | I48: 45945 | J48: 46309 | K48: =IF(OR(I48="",J48=""),"",IF(J48<I48,0,(YEAR(J48)-YEAR(I48))*12+(MONTH(J48)-MONTH(I48))+1-IF(DAY(J48)<DAY(I48),1,0))) -> 12 | L48: 50082.192 | M48: -20510.931 | P48: 50082.192
A49: 59 | B49: Burst Training and Design | C49: 19 x Articulate 360 TEAMs Annual Subscription | D49: PX, DC, PSN, Cyber | E49: Matt Toohey/Craig Murphy | F49: 511HDO | G49: 8200 | H49: Fixed | I49: 46037 | J49: 46401 | K49: =IF(OR(I49="",J49=""),"",IF(J49<I49,0,(YEAR(J49)-YEAR(I49))*12+(MONTH(J49)-MONTH(I49))+1-IF(DAY(J49)<DAY(I49),1,0))) -> 12 | L49: 43880.527 | M49: 8618.5535 | P49: 43880.527
A50: 60 | B50: C A Technology Pty Ltd (CAMMS) | C50: CAMMS GRC Tool | D50: Risk | E50: Neeraja/Dan Aitken/ Jess Wilson | F50: 516HDO | G50: 8200 | H50: Fixed | I50: 45382 | J50: 46476 | K50: =IF(OR(I50="",J50=""),"",IF(J50<I50,0,(YEAR(J50)-YEAR(I50))*12+(MONTH(J50)-MONTH(I50))+1-IF(DAY(J50)<DAY(I50),1,0))) -> 36 | L50: 116104.27 | M50: -3782.2482 | P50: 116104.27
A51: 61 | B51: Canva Pty Ltd | C51: Canva Enterprise x 200 | D51: Marketing | E51: Michelle Callanan | F51: 516HDO | G51: 8200 | H51: Fixed | I51: 45430 | J51: 46159 | K51: =IF(OR(I51="",J51=""),"",IF(J51<I51,0,(YEAR(J51)-YEAR(I51))*12+(MONTH(J51)-MONTH(I51))+1-IF(DAY(J51)<DAY(I51),1,0))) -> 24 | L51: 55000 | M51: 3994.9463 | P51: 55000
A52: 63 | B52: China Telecom Global Limited | C52: AWS Network Circuit - Singapore to Shanghai | D52: SP/LT? | E52: Neeraja/Jayakumar | F52: 516HDO | G52: 8800 | H52: Fixed | I52: 45870 | J52: 46599 | K52: =IF(OR(I52="",J52=""),"",IF(J52<I52,0,(YEAR(J52)-YEAR(I52))*12+(MONTH(J52)-MONTH(I52))+1-IF(DAY(J52)<DAY(I52),1,0))) -> 24 | L52: 31644 | M52: 4747.0014 | O52: -31644 | P52: 0
A53: 66 | B53: CISO Lens Pty Ltd | C53: CISO Lens Membership - Simon Cowley, Rosie, AMG, Samba | D53: Cyber | E53: Simon Cowley | F53: 514HDO | G53: 8200 | H53: Fixed | I53: 46023 | J53: 46387 | K53: =IF(OR(I53="",J53=""),"",IF(J53<I53,0,(YEAR(J53)-YEAR(I53))*12+(MONTH(J53)-MONTH(I53))+1-IF(DAY(J53)<DAY(I53),1,0))) -> 12 | L53: 74680.822 | M53: 40140.113 | P53: 74680.822
A54: 11 | B54: Civica Pty Ltd | C54: Provisional for CR | D54: LT | E54: Jason Thunder | F54: 308IEA | G54: 8200 | H54: Fixed | K54: =IF(OR(I54="",J54=""),"",IF(J54<I54,0,(YEAR(J54)-YEAR(I54))*12+(MONTH(J54)-MONTH(I54))+1-IF(DAY(J54)<DAY(I54),1,0))) | L54: 25000 | M54: 25000 | P54: 25000
A55: 11 | B55: Civica Pty Ltd | D55: LT | E55: Jason Thunder | F55: 319IEO | G55: 8200 | H55: Consumption | K55: =IF(OR(I55="",J55=""),"",IF(J55<I55,0,(YEAR(J55)-YEAR(I55))*12+(MONTH(J55)-MONTH(I55))+1-IF(DAY(J55)<DAY(I55),1,0))) | L55: 973271.2 | M55: 44401.091 | P55: 973271.2
A56: 67 | B56: Concur Holdings (Netherlands) B.V | C56: Concur SaaS Licence | D56: Finance | E56: Neeraja/Emin Aldim | F56: 516HDO | G56: 8200 | H56: Fixed | I56: 45839 | J56: 46203 | K56: =IF(OR(I56="",J56=""),"",IF(J56<I56,0,(YEAR(J56)-YEAR(I56))*12+(MONTH(J56)-MONTH(I56))+1-IF(DAY(J56)<DAY(I56),1,0))) -> 12 | L56: 420000 | M56: 37652.321 | P56: 420000
A57: 294 | B57: ConnectOS Pty Ltd | C57: Contractors in Manila | D57: CloudOps | E57: Jayakumar VR | F57: 513HDO | G57: 8700 | H57: Consumption | K57: =IF(OR(I57="",J57=""),"Monthly",IF(J57<I57,0,(YEAR(J57)-YEAR(I57))*12+(MONTH(J57)-MONTH(I57))+1-IF(DAY(J57)<DAY(I57),1,0))) -> Monthly | L57: 220000 | M57: 105269.41 | P57: 220000
A58: 295 | B58: ConnectOS Pty Ltd | C58: Only Cyber Contractors in Manila | D58: Cyber | E58: Simon Cowley | F58: 514HDO | G58: 8700 | H58: Consumption | K58: =IF(OR(I58="",J58=""),"Monthly",IF(J58<I58,0,(YEAR(J58)-YEAR(I58))*12+(MONTH(J58)-MONTH(I58))+1-IF(DAY(J58)<DAY(I58),1,0))) -> Monthly | L58: 1837880 | M58: 759035.53 | O58: -570000 | P58: 1267880
A59: 13 | B59: ContactMonkey | C59: Outlook Add-In | D59: Marketing | E59: Neeraja / Devi B/ Stephanie Watt | F59: 213BTI | G59: 8200 | H59: Fixed | I59: 45494 | J59: 46223 | K59: =IF(OR(I59="",J59=""),"",IF(J59<I59,0,(YEAR(J59)-YEAR(I59))*12+(MONTH(J59)-MONTH(I59))+1-IF(DAY(J59)<DAY(I59),1,0))) -> 24 | L59: 44383.562 | M59: 37163.836 | N59: -20000 | P59: 24383.562
A60: FY27B | B60: Contenful Nine Tail Personalisation | C60: Website personalisation | D60: Marketing | E60: Joel Knight/ Kristin Prestinenzi | F60: 511HDO | G60: 8200 | K60: =IF(OR(I60="",J60=""),"Monthly",IF(J60<I60,0,(YEAR(J60)-YEAR(I60))*12+(MONTH(J60)-MONTH(I60))+1-IF(DAY(J60)<DAY(I60),1,0))) -> Monthly | L60: 100000 | M60: 100000 | P60: 100000
A61: 68 | B61: Contentful, Inc. | C61: Licences + Support - To create, manage and distribute content to IDP's platform | D61: Marketing | E61: Neeraja / Mythili D | F61: 213BTI | G61: 8200 | H61: Fixed | I61: 45681 | J61: 47141 | K61: =IF(OR(I61="",J61=""),"",IF(J61<I61,0,(YEAR(J61)-YEAR(I61))*12+(MONTH(J61)-MONTH(I61))+1-IF(DAY(J61)<DAY(I61),1,0))) -> 48 | L61: 358060.2 | M61: -34079.343 | P61: 358060.2
A62: 69 | B62: Convert Insights Inc. | C62: Convert A/B testing Enterprise Plan - web traffic analytics | D62: Marketing | E62: Matt Toohey | F62: 511HDO | G62: 8200 | H62: Fixed | I62: 45799 | J62: 46528 | K62: =IF(OR(I62="",J62=""),"",IF(J62<I62,0,(YEAR(J62)-YEAR(I62))*12+(MONTH(J62)-MONTH(I62))+1-IF(DAY(J62)<DAY(I62),1,0))) -> 24 | L62: 41901.418 | M62: -5481.2594 | P62: 41901.418
A63: 70 | B63: Creatify Lab Inc | C63: Creatify Unlimited Team Plan (10 seats) | D63: Marketing | E63: Michelle Callanan | F63: 511HDO | G63: 8200 | H63: Fixed | I63: 45870 | J63: 46234 | K63: =IF(OR(I63="",J63=""),"",IF(J63<I63,0,(YEAR(J63)-YEAR(I63))*12+(MONTH(J63)-MONTH(I63))+1-IF(DAY(J63)<DAY(I63),1,0))) -> 12 | L63: 18158.904 | M63: 2862.8989 | P63: 18158.904
A64: 71 | B64: CSC Corporate Domains, Inc. | C64: Domain Registrations | D64: Cyber | E64: Simon Cowley | F64: 514HDO | G64: 8200 | H64: Fixed | I64: 45839 | J64: 46203 | K64: =IF(OR(I64="",J64=""),"",IF(J64<I64,0,(YEAR(J64)-YEAR(I64))*12+(MONTH(J64)-MONTH(I64))+1-IF(DAY(J64)<DAY(I64),1,0))) -> 12 | L64: 50400 | M64: 14189.616 | P64: 50400
A65: 301 | B65: CyberCX Pty Ltd | C65: Maturity assessment | D65: Cyber | E65: Simon Cowley | F65: 514HDO | G65: 8700 | H65: Consumption | K65: =IF(OR(I65="",J65=""),"Monthly",IF(J65<I65,0,(YEAR(J65)-YEAR(I65))*12+(MONTH(J65)-MONTH(I65))+1-IF(DAY(J65)<DAY(I65),1,0))) -> Monthly | L65: 190000 | M65: 180254.04 | P65: 190000
A66: 77 | B66: Data#3 Limited | C66: Adobe 1yr Licenses (9xCC,1xAP) | D66: Shared | E66: Lewis Lee | F66: 517HDO | G66: 8200 | H66: Fixed | I66: 45916 | J66: 46277 | K66: =IF(OR(I66="",J66=""),"",IF(J66<I66,0,(YEAR(J66)-YEAR(I66))*12+(MONTH(J66)-MONTH(I66))+1-IF(DAY(J66)<DAY(I66),1,0))) -> 12 | L66: 20260.655 | M66: -1832.9001 | P66: 20260.655
A67: 79 | B67: Data#3 Limited | C67: Adobe 3yr Licenses (20xAP,53xCC,8xAS,1xAU,1xDW,2xIL,1xPP) | D67: Shared | E67: Lewis Lee | F67: 517HDO | G67: 8200 | H67: Fixed | I67: 45912 | J67: 47006 | K67: =IF(OR(I67="",J67=""),"",IF(J67<I67,0,(YEAR(J67)-YEAR(I67))*12+(MONTH(J67)-MONTH(I67))+1-IF(DAY(J67)<DAY(I67),1,0))) -> 36 | L67: 108490.66 | M67: 36064.548 | P67: 108490.66
A68: 76 | B68: Data#3 Limited | C68: Inforiver Analytics+ (Tier 20 - 99) - Annual Subscription PowerBI | D68: Finance | E68: Lewis Lee | F68: 517HDO | G68: 8200 | H68: Fixed | I68: 45758 | J68: 46122 | K68: =IF(OR(I68="",J68=""),"",IF(J68<I68,0,(YEAR(J68)-YEAR(I68))*12+(MONTH(J68)-MONTH(I68))+1-IF(DAY(J68)<DAY(I68),1,0))) -> 12 | L68: 5359.7358 | M68: 255.22551 | P68: 5359.7358
A69: 420 | B69: Data#3 Limited | C69: Last Pass Subscription (Password Software Mgt) IAM Team | D69: Cyber | E69: Simon Cowley | F69: 514HDO | G69: 8200 | I69: 45962 | J69: 46326 | K69: =IF(OR(I69="",J69=""),"Monthly",IF(J69<I69,0,(YEAR(J69)-YEAR(I69))*12+(MONTH(J69)-MONTH(I69))+1-IF(DAY(J69)<DAY(I69),1,0))) -> 12 | L69: 20822.122 | M69: 12681.216 | P69: 20822.122
A70: 75 | B70: Data#3 Limited | C70: M365 (342) + O365 (310) Education Licenses | D70: English Language Teaching | E70: Lewis Lee | F70: 517HDO | G70: 8200 | H70: Fixed | I70: 45948 | J70: 46312 | K70: =IF(OR(I70="",J70=""),"",IF(J70<I70,0,(YEAR(J70)-YEAR(I70))*12+(MONTH(J70)-MONTH(I70))+1-IF(DAY(J70)<DAY(I70),1,0))) -> 12 | L70: 9951.694 | M70: -13014.819 | P70: 9951.694
A71: 80 | B71: Data#3 Limited | C71: Renewal 3 years - Ivanti Neurons Platform W/CSV Connector | D71: Digital Workplace | E71: Lewis Lee | F71: 517HDO | G71: 8200 | H71: Fixed | I71: 45948 | J71: 47043 | K71: =IF(OR(I71="",J71=""),"",IF(J71<I71,0,(YEAR(J71)-YEAR(I71))*12+(MONTH(J71)-MONTH(I71))+1-IF(DAY(J71)<DAY(I71),1,0))) -> 36 | L71: 58733.995 | M71: 58733.995 | P71: 58733.995
A72: 423 | B72: Data#3 Limited | C72: Resource - Sai | D72: Digital Workplace | E72: Lewis Lee | F72: 517HDO | G72: 8700 | H72: Consumption | K72: =IF(OR(I72="",J72=""),"Monthly",IF(J72<I72,0,(YEAR(J72)-YEAR(I72))*12+(MONTH(J72)-MONTH(I72))+1-IF(DAY(J72)<DAY(I72),1,0))) -> Monthly | L72: 152760 | M72: 4020 | P72: 152760
A73: 78 | B73: Data#3 Limited | C73: TechSmith Camtasia licenses | D73: Marketing | E73: Neeraja/Mary Priya | F73: 213BTI | G73: 8200 | H73: Fixed | I73: 45942 | J73: 46306 | K73: =IF(OR(I73="",J73=""),"",IF(J73<I73,0,(YEAR(J73)-YEAR(I73))*12+(MONTH(J73)-MONTH(I73))+1-IF(DAY(J73)<DAY(I73),1,0))) -> 12 | L73: 300.41638 | M73: 240.69989 | P73: 300.41638
A74: 82 | B74: DataEDO | C74: Dataedo Starter (3 editors + unlimited viewers / community users) | D74: SP | E74: Neeraja / Pradeep N/ Stuart Nickols | F74: 213BTI | G74: 8200 | H74: Fixed | I74: 45782 | J74: 46146 | K74: =IF(OR(I74="",J74=""),"",IF(J74<I74,0,(YEAR(J74)-YEAR(I74))*12+(MONTH(J74)-MONTH(I74))+1-IF(DAY(J74)<DAY(I74),1,0))) -> 12 | L74: 13600 | M74: 2239.3867 | P74: 13600
A75: 202 | B75: DataRobot, Inc. | C75: Machine Learning | D75: Data (CDO) | E75: Stuart Nickols | F75: 213BTI | G75: 8200 | H75: Fixed | I75: 45830 | J75: 46925 | K75: =IF(OR(I75="",J75=""),"",IF(J75<I75,0,(YEAR(J75)-YEAR(I75))*12+(MONTH(J75)-MONTH(I75))+1-IF(DAY(J75)<DAY(I75),1,0))) -> 36 | L75: 143868.61 | M75: 14955.182 | P75: 143868.61
A76: 203 | B76: Digital Maas Pty Ltd | C76: SEO Tool - Premium Subscription | D76: Marketing | E76: Michelle Callanan/ Joel Knight | F76: 511HDO | G76: 8200 | H76: Fixed | I76: 45719 | J76: 46083 | K76: =IF(OR(I76="",J76=""),"",IF(J76<I76,0,(YEAR(J76)-YEAR(I76))*12+(MONTH(J76)-MONTH(I76))+1-IF(DAY(J76)<DAY(I76),1,0))) -> 12 | L76: 33330.362 | M76: 15590.526 | P76: 33330.362
A77: 308 | B77: Direselign Addis | D77: Tech | F77: 490HDO | G77: 8700 | H77: Consumption | K77: =IF(OR(I77="",J77=""),"Monthly",IF(J77<I77,0,(YEAR(J77)-YEAR(I77))*12+(MONTH(J77)-MONTH(I77))+1-IF(DAY(J77)<DAY(I77),1,0))) -> Monthly | L77: 37242.513 | M77: 37242.513 | P77: 37242.513
A78: 84 | B78: Dragon Metrics Limited | C78: Dragon Metrics Subscription – Enterprise (Weekly ranking update) | D78: Marketing | E78: Michelle Callanan/ Joel Knight/Prem Pradeep | F78: 516HDO | G78: 8200 | H78: Fixed | I78: 45965 | J78: 46203 | K78: =IF(OR(I78="",J78=""),"",IF(J78<I78,0,(YEAR(J78)-YEAR(I78))*12+(MONTH(J78)-MONTH(I78))+1-IF(DAY(J78)<DAY(I78),1,0))) -> 8 | L78: 13440 | M78: 3136.3606 | O78: -13440 | P78: 0
A79: 85 | B79: ECCTIS LTD | C79: Bespoke Membership | D79: Client Partnerships | E79: Neeraja | F79: 516HDO | G79: 8200 | H79: Fixed | I79: 45839 | J79: 46203 | K79: =IF(OR(I79="",J79=""),"",IF(J79<I79,0,(YEAR(J79)-YEAR(I79))*12+(MONTH(J79)-MONTH(I79))+1-IF(DAY(J79)<DAY(I79),1,0))) -> 12 | L79: 4000 | M79: 3104.8877 | P79: 4000
A80: 259 | B80: Employee Communication Charges | F80: 514HDO | G80: 8800 | H80: Other | K80: =IF(OR(I80="",J80=""),"Monthly",IF(J80<I80,0,(YEAR(J80)-YEAR(I80))*12+(MONTH(J80)-MONTH(I80))+1-IF(DAY(J80)<DAY(I80),1,0))) -> Monthly | L80: 1800 | M80: 799.82 | P80: 1800
A81: 260 | B81: Employee Communication Charges | F81: 517HDO | G81: 8800 | H81: Other | K81: =IF(OR(I81="",J81=""),"Monthly",IF(J81<I81,0,(YEAR(J81)-YEAR(I81))*12+(MONTH(J81)-MONTH(I81))+1-IF(DAY(J81)<DAY(I81),1,0))) -> Monthly | L81: 3600 | M81: 2507.26 | P81: 3600
A82: FY27B | B82: Envato Elements | C82: Online platform providing licensed digital assets, video templates, stock footage, music, and graphics | D82: Tech | E82: Neeraja/Mary Priya | F82: 516HDO | G82: 8200 | K82: =IF(OR(I82="",J82=""),"Monthly",IF(J82<I82,0,(YEAR(J82)-YEAR(I82))*12+(MONTH(J82)-MONTH(I82))+1-IF(DAY(J82)<DAY(I82),1,0))) -> Monthly | L82: 7830 | M82: 7830 | P82: 7830
A83: 88 | B83: Epignosis LLC | C83: IELTS LMS - iLearn | D83: LT | E83: Steph Watt | F83: 308IEA | G83: 8200 | H83: Fixed | I83: 45730 | J83: 46825 | K83: =IF(OR(I83="",J83=""),"",IF(J83<I83,0,(YEAR(J83)-YEAR(I83))*12+(MONTH(J83)-MONTH(I83))+1-IF(DAY(J83)<DAY(I83),1,0))) -> 36 | L83: 72390.151 | M83: 22572.36 | P83: 72390.151
A84: 89 | B84: EPI-USE Australia Pty Ltd | C84: SuccessFactor Support - for global payroll integrations | D84: PX | E84: Neeraja/Monique | F84: 516HDO | G84: 8200 | H84: Fixed | I84: 45909 | J84: 46273 | K84: =IF(OR(I84="",J84=""),"",IF(J84<I84,0,(YEAR(J84)-YEAR(I84))*12+(MONTH(J84)-MONTH(I84))+1-IF(DAY(J84)<DAY(I84),1,0))) -> 12 | L84: 6959.3425 | M84: -29105.797 | P84: 6959.3425
A85: 90 | B85: Equinix Australia Pty Ltd | C85: Saas - data center services | D85: Cyber | E85: Simon Cowley | F85: 514HDO | G85: 8200 | H85: Fixed | I85: 45717 | J85: 46081 | K85: =IF(OR(I85="",J85=""),"",IF(J85<I85,0,(YEAR(J85)-YEAR(I85))*12+(MONTH(J85)-MONTH(I85))+1-IF(DAY(J85)<DAY(I85),1,0))) -> 12 | L85: 52500 | M85: 10602.65 | N85: -52500 | P85: 0
A86: 92 | B86: FastSpring | C86: Numbeo API Basic Plan - living database | D86: SP | E86: Neeraja | F86: 213BTI | G86: 8200 | H86: Fixed | I86: 46007 | J86: 46371 | K86: =IF(OR(I86="",J86=""),"",IF(J86<I86,0,(YEAR(J86)-YEAR(I86))*12+(MONTH(J86)-MONTH(I86))+1-IF(DAY(J86)<DAY(I86),1,0))) -> 12 | L86: 7767.4521 | M86: 6483.9452 | P86: 7767.4521
A87: 93 | B87: Figma, Inc. | C87: Organization Full seats x 1 (UX tool - realtime collab) | D87: SP | E87: Neeraja/Amudha/Sian Harris | F87: 516HDO | G87: 8200 | H87: Fixed | I87: 45811 | J87: 46540 | K87: =IF(OR(I87="",J87=""),"",IF(J87<I87,0,(YEAR(J87)-YEAR(I87))*12+(MONTH(J87)-MONTH(I87))+1-IF(DAY(J87)<DAY(I87),1,0))) -> 24 | L87: 16929.199 | M87: 269.02152 | P87: 16929.199
A88: 94 | B88: FRAUDWATCH INTERNATIONAL PTY LTD | C88: Digital Brand Protection | D88: Cyber | E88: Simon Cowley | F88: 514HDO | G88: 8200 | H88: Fixed | I88: 45273 | J88: 46368 | K88: =IF(OR(I88="",J88=""),"",IF(J88<I88,0,(YEAR(J88)-YEAR(I88))*12+(MONTH(J88)-MONTH(I88))+1-IF(DAY(J88)<DAY(I88),1,0))) -> 36 | L88: 72737.124 | M88: 2169.2519 | P88: 72737.124
A89: 96 | B89: Freepik Company, SL | C89: Freepik Premium+ Yearly | D89: Marketing | E89: Michelle Callanan | F89: 511HDO | G89: 8200 | H89: Fixed | I89: 45876 | J89: 46240 | K89: =IF(OR(I89="",J89=""),"",IF(J89<I89,0,(YEAR(J89)-YEAR(I89))*12+(MONTH(J89)-MONTH(I89))+1-IF(DAY(J89)<DAY(I89),1,0))) -> 12 | L89: 10897.616 | M89: 2596.1667 | P89: 10897.616
A90: FY27B | B90: FTI Consulting | C90: Critical pen Testing | D90: LT | E90: Jason Thunder | F90: 308IEA | G90: 8700 | K90: =IF(OR(I90="",J90=""),"Monthly",IF(J90<I90,0,(YEAR(J90)-YEAR(I90))*12+(MONTH(J90)-MONTH(I90))+1-IF(DAY(J90)<DAY(I90),1,0))) -> Monthly | L90: 64000 | M90: 64000 | P90: 64000
A91: FY27B | B91: FTI Consulting | C91: Critical pen Testing | D91: Cyber | E91: Simon Cowley | F91: 514HDO | G91: 8700 | K91: =IF(OR(I91="",J91=""),"Monthly",IF(J91<I91,0,(YEAR(J91)-YEAR(I91))*12+(MONTH(J91)-MONTH(I91))+1-IF(DAY(J91)<DAY(I91),1,0))) -> Monthly | L91: 84000 | M91: 84000 | P91: 84000
A92: FY27B | B92: FTI Consulting | C92: DFIR | D92: Cyber | E92: Simon Cowley | F92: 514HDO | G92: 8700 | K92: =IF(OR(I92="",J92=""),"Monthly",IF(J92<I92,0,(YEAR(J92)-YEAR(I92))*12+(MONTH(J92)-MONTH(I92))+1-IF(DAY(J92)<DAY(I92),1,0))) -> Monthly | L92: 157500 | M92: 157500 | P92: 157500
A93: FY27B | B93: FTI Consulting | C93: Red Team exercise | D93: Cyber | E93: Simon Cowley | F93: 514HDO | G93: 8700 | K93: =IF(OR(I93="",J93=""),"Monthly",IF(J93<I93,0,(YEAR(J93)-YEAR(I93))*12+(MONTH(J93)-MONTH(I93))+1-IF(DAY(J93)<DAY(I93),1,0))) -> Monthly | L93: 131250 | M93: 131250 | P93: 131250
A94: 319 | B94: Gashaw Taye | D94: Tech | F94: 490HDO | G94: 8700 | H94: Consumption | K94: =IF(OR(I94="",J94=""),"Monthly",IF(J94<I94,0,(YEAR(J94)-YEAR(I94))*12+(MONTH(J94)-MONTH(I94))+1-IF(DAY(J94)<DAY(I94),1,0))) -> Monthly | L94: 20731.599 | M94: 20731.599 | P94: 20731.599
A95: 98 | B95: GitLab Pty Ltd | C95: SaaS - Premium (formerly Silver) - 1 Year - 450 Licenses (375users from 20/04/26-19/04/28) | D95: SP | E95: Neeraja/Jayakumar | F95: 213BTI | G95: 8200 | H95: Fixed | I95: 45767 | J95: 46131 | K95: =IF(OR(I95="",J95=""),"",IF(J95<I95,0,(YEAR(J95)-YEAR(I95))*12+(MONTH(J95)-MONTH(I95))+1-IF(DAY(J95)<DAY(I95),1,0))) -> 12 | L95: 365020 | M95: 53883.162 | P95: 365020
A96: 14 | B96: Google Australia Pty Ltd | C96: Google Cloud | D96: Platform & Infrastructure | E96: Neeraja/Jayakumar | F96: 513HDO | G96: 8200 | H96: Consumption | K96: =IF(OR(I96="",J96=""),"",IF(J96<I96,0,(YEAR(J96)-YEAR(I96))*12+(MONTH(J96)-MONTH(I96))+1-IF(DAY(J96)<DAY(I96),1,0))) | L96: 24000 | M96: 3300.2 | P96: 24000
A97: 14 | B97: Google Australia Pty Ltd | C97: Google Recaptcha | D97: Tech | E97: Neeraja/ Kishore | F97: 516HDO | G97: 8200 | H97: Other | K97: =IF(OR(I97="",J97=""),"Monthly",IF(J97<I97,0,(YEAR(J97)-YEAR(I97))*12+(MONTH(J97)-MONTH(I97))+1-IF(DAY(J97)<DAY(I97),1,0))) -> Monthly | L97: 2000 | M97: 2000 | P97: 2000
A98: FY27B | B98: Google support | C98: Google Translation | D98: Tech | E98: Neeraja/Kiruthika | F98: 516HDO | G98: 8200 | L98: 875 | M98: 875 | P98: 875
A99: 99 | B99: Growthbook | C99: Growthbook Cloud x 4seats @$20/seat | D99: Marketing | E99: David Mackie/Sian | F99: 511HDO | G99: 8200 | H99: Fixed | I99: 45839 | J99: 46203 | K99: =IF(OR(I99="",J99=""),"",IF(J99<I99,0,(YEAR(J99)-YEAR(I99))*12+(MONTH(J99)-MONTH(I99))+1-IF(DAY(J99)<DAY(I99),1,0))) -> 12 | L99: 3024 | M99: 1324.7399 | P99: 3024
A100: FY27B | B100: Gupshup | C100: Platform fee i.e. Gupshup margin based on Whatsapp vol @ $0.001. (Usage fee is absorbed by network billed by Meta via Gupshup) | D100: Tech | E100: Neeraja/Antony | F100: 516HDO | G100: 8200 | K100: =IF(OR(I100="",J100=""),"Monthly",IF(J100<I100,0,(YEAR(J100)-YEAR(I100))*12+(MONTH(J100)-MONTH(I100))+1-IF(DAY(J100)<DAY(I100),1,0))) -> Monthly | L100: 14000 | M100: 14000 | P100: 14000
...
